Workbook

Sheet Overview
B2: Customer risk scoring model
B3: Northgate Bank UK Limited (fictional) | HND-CRA-004 | version 0.4 draft | September 2026
B5: What this workbook does
B6: Step 3 of the Hindsight project. It takes the 400 synthetic customers in data/synthetic-customers.csv, converts each recorded level into a score using the Step 2 risk factor library, applies the category weights, produces an overall score and a band, and then applies the mandatory escalators from section 5.3 of the methodology.
B8: Sheets
B9: Mapping - the 98 level definitions from the Step 2 library, each with its score. This is the lookup table.
B10: Weights - the 20 factors with their weight inside their category and their effective weight across the model.
B11: Customers - the imported population. One row per customer, one column per factor, holding the level recorded at onboarding.
B12: Scoring - the engine. Each factor label is converted to a score, weighted, summed, banded, then escalated.
B13: Dashboard - what the population looks like once scored, and how much each category is actually doing.
B14: Backtest - Step 4. Six FCA enforcement cases, each rebuilt as it looked at onboarding and scored two or three ways.
B15: Validation - Step 5. Weight sensitivity, three alternative aggregation rules, and the 2026 EDD test.
... B33: Synthetic data only. Northgate Bank UK Limited does not exist, no real customer data appears in this workbook, and this is a self-directed learning project rather than professional compliance advice.

Sheet Mapping
A1: Factor | B1: Level recorded | C1: Score | D1: Lookup key
A2: C1 | B2: Individual | C2: 1 | D2: =$A2&"|"&$B2 -> C1|Individual
A3: C1 | B3: Sole trader or joint | C3: 2 | D3: =$A3&"|"&$B3 -> C1|Sole trader or joint
A4: C1 | B4: UK company, natural owners | C4: 3 | D4: =$A4&"|"&$B4 -> C1|UK company, natural owners
A5: C1 | B5: UK company, corporate owner | C5: 4 | D5: =$A5&"|"&$B5 -> C1|UK company, corporate owner
A6: C1 | B6: Trust, nominee or overseas | C6: 5 | D6: =$A6&"|"&$B6 -> C1|Trust, nominee or overseas
A7: C2 | B7: Natural person | C7: 1 | D7: =$A7&"|"&$B7 -> C2|Natural person
A8: C2 | B8: One or two UBOs | C8: 2 | D8: =$A8&"|"&$B8 -> C2|One or two UBOs
A9: C2 | B9: Three to five UBOs | C9: 3 | D9: =$A9&"|"&$B9 -> C2|Three to five UBOs
A10: C2 | B10: Two layers, evidenced | C10: 4 | D10: =$A10&"|"&$B10 -> C2|Two layers, evidenced
A11: C2 | B11: Nominee, bearer or unevidenced | C11: 5 | D11: =$A11&"|"&$B11 -> C2|Nominee, bearer or unevidenced
A12: C3 | B12: Employed or pension | C12: 1 | D12: =$A12&"|"&$B12 -> C3|Employed or pension
A13: C3 | B13: Regulated profession | C13: 2 | D13: =$A13&"|"&$B13 -> C3|Regulated profession
... A99: A5 | B99: Not credible | C99: 5 | D99: =$A99&"|"&$B99 -> A5|Not credible

Sheet Weights
A1: Factor | B1: Category | C1: Effective weight | D1: Weight in category | G1: Category | H1: Category weight
A2: C1 | B2: C | C2: 0.06 | D2: 0.2 | G2: Customer | H2: 0.3
A3: C2 | B3: C | C3: 0.06 | D3: 0.2 | G3: Geography | H3: 0.25
A4: C3 | B4: C | C4: 0.075 | D4: 0.25 | G4: Product and service | H4: 0.2
A5: C4 | B5: C | C5: 0.06 | D5: 0.2 | G5: Delivery channel | H5: 0.1
A6: C5 | B6: C | C6: 0.045 | D6: 0.15 | G6: Expected activity | H6: 0.15
A7: G1 | B7: G | C7: 0.1 | D7: 0.4
A8: G2 | B8: G | C8: 0.05 | D8: 0.2
A9: G3 | B9: G | C9: 0.1 | D9: 0.4
A10: P1 | B10: P | C10: 0.07 | D10: 0.35
A11: P2 | B11: P | C11: 0.05 | D11: 0.25
A12: P3 | B12: P | C12: 0.05 | D12: 0.25
A13: P4 | B13: P | C13: 0.03 | D13: 0.15
A14: D1 | B14: D | C14: 0.045 | D14: 0.45
A15: D2 | B15: D | C15: 0.035 | D15: 0.35
A16: D3 | B16: D | C16: 0.02 | D16: 0.2
A17: A1 | B17: A | C17: 0.0375 | D17: 0.25
A18: A2 | B18: A | C18: 0.045 | D18: 0.3
... A21: A5 | B21: A | C21: 0.015 | D21: 0.1
B22: Total | C22: =SUM($C$2:$C$21) -> 1
A24: Copied from model/risk-factor-library.xlsx v0.3. Check 4 below confirms the total is still 100%.
A26: Horizontal copy used by the Scoring sheet | C26: =$A2 -> C1 | D26: =$A3 -> C2 | E26: =$A4 -> C3 | F26: =$A5 -> C4 | G26: =$A6 -> C5 | H26: =$A7 -> G1 | I26: =$A8 -> G2 | J26: =$A9 -> G3 | K26: =$A10 -> P1 | L26: =$A11 -> P2 | M26: =$A12 -> P3 | N26: =$A13 -> P4 | O26: =$A14 -> D1 | P26: =$A15 -> D2 | Q26: =$A16 -> D3 | R26: =$A17 -> A1 | S26: =$A18 -> A2 | T26: =$A19 -> A3 | U26: =$A20 -> A4 | V26: =$A21 -> A5
A27: Effective weight | C27: =$C2 -> 0.06 | D27: =$C3 -> 0.06 | E27: =$C4 -> 0.075 | F27: =$C5 -> 0.06 | G27: =$C6 -> 0.045 | H27: =$C7 -> 0.1 | I27: =$C8 -> 0.05 | J27: =$C9 -> 0.1 | K27: =$C10 -> 0.07 | L27: =$C11 -> 0.05 | M27: =$C12 -> 0.05 | N27: =$C13 -> 0.03 | O27: =$C14 -> 0.045 | P27: =$C15 -> 0.035 | Q27: =$C16 -> 0.02 | R27: =$C17 -> 0.0375 | S27: =$C18 -> 0.045 | T27: =$C19 -> 0.03 | U27: =$C20 -> 0.0225 | V27: =$C21 -> 0.015
A28: Weight in category | C28: =$D2 -> 0.2 | D28: =$D3 -> 0.2 | E28: =$D4 -> 0.25 | F28: =$D5 -> 0.2 | G28: =$D6 -> 0.15 | H28: =$D7 -> 0.4 | I28: =$D8 -> 0.2 | J28: =$D9 -> 0.4 | K28: =$D10 -> 0.35 | L28: =$D11 -> 0.25 | M28: =$D12 -> 0.25 | N28: =$D13 -> 0.15 | O28: =$D14 -> 0.45 | P28: =$D15 -> 0.35 | Q28: =$D16 -> 0.2 | R28: =$D17 -> 0.25 | S28: =$D18 -> 0.3 | T28: =$D19 -> 0.2 | U28: =$D20 -> 0.15 | V28: =$D21 -> 0.1

Sheet Customers
A1: customer_id | B1: segment | C1: C1 | D1: C2 | E1: C3 | F1: C4 | G1: C5 | H1: G1 | I1: G2 | J1: G3 | K1: P1 | L1: P2 | M1: P3 | N1: P4 | O1: D1 | P1: D2 | Q1: D3 | R1: A1 | S1: A2 | T1: A3 | U1: A4 | V1: A5 | W1: sar_last_12m | X1: onboarded
A2: NG-10252 | B2: Personal | C2: Individual | D2: Natural person | E2: Employed or pension | F2: No match | G2: No match | H2: United Kingdom | I2: UK tax residence only | J2: UK only | K2: Current account with credit | L2: Under 2k a month | M2: Enabled, unused | N2: Sole party | O2: Digital, own app | P2: Electronic, two sources | Q2: Comparison site | R2: Under 5k, consistent | S2: No cash credits | T2: None | U2: Employer and retail | V2: Consistent | W2: No | X2: 2025-10-07
A3: NG-10111 | B3: Personal | C3: Sole trader or joint | D3: Natural person | E3: General trade | F3: No match | G3: No match | H3: United Kingdom | I3: UK tax residence only | J3: UK only | K3: Current account, no overdraft | L3: Under 2k a month | M3: Not enabled | N3: Sole party | O3: Branch | P3: Documents face to face | Q3: Comparison site | R3: 5k to 25k, consistent | S3: Up to 10 percent | T3: Over 40 percent | U3: Employer and retail | V3: Consistent | W3: No | X3: 2024-09-25
A4: NG-10086 | B4: Personal | C4: Individual | D4: Natural person | E4: Employed or pension | F4: No match | G4: No match | H4: United Kingdom | I4: UK tax residence only | J4: UK only | K4: Current account, no overdraft | L4: Under 2k a month | M4: Enabled, unused | N4: Joint, related | O4: Digital, own app | P4: Electronic, two sources | Q4: Customer referral | R4: Under 5k, consistent | S4: No cash credits | T4: Up to 10 percent | U4: Employer and retail | V4: Consistent | W4: No | X4: 2025-08-03
A5: NG-10203 | B5: Personal | C5: Individual | D5: Natural person | E5: Regulated profession | F5: No match | G5: No match | H5: United Kingdom | I5: UK tax residence only | J5: Unlisted countries | K5: Current account with credit | L5: Under 2k a month | M5: Enabled, unused | N5: Joint, related | O5: Branch | P5: Electronic, two sources | Q5: Direct | R5: Under 5k, consistent | S5: Up to 10 percent | T5: None | U5: Employer and retail | V5: Consistent | W5: No | X5: 2025-11-30
A6: NG-10171 | B6: Personal | C6: Individual | D6: Natural person | E6: Employed or pension | F6: No match | G6: No match | H6: United Kingdom | I6: UK tax residence only | J6: UK only | K6: Current account, no overdraft | L6: Under 2k a month | M6: Enabled, unused | N6: Sole party | O6: Digital, own app | P6: Documents face to face | Q6: Comparison site | R6: Under 5k, consistent | S6: Up to 10 percent | T6: None | U6: Employer and retail | V6: Consistent | W6: No | X6: 2025-07-27
A7: NG-10124 | B7: Personal | C7: Individual | D7: Natural person | E7: Employed or pension | F7: No match | G7: No match | H7: United Kingdom | I7: UK tax residence only | J7: UK only | K7: Current account with credit | L7: Withdrawal only | M7: Enabled, unused | N7: Sole party | O7: Digital, own app | P7: Electronic, two sources | Q7: Direct | R7: Under 5k, consistent | S7: No cash credits | T7: None | U7: Employer and retail | V7: Consistent | W7: No | X7: 2024-10-29
A8: NG-10062 | B8: Personal | C8: Individual | D8: Natural person | E8: General trade | F8: No match | G8: No match | H8: United Kingdom | I8: UK tax residence only | J8: UK only | K8: Current account with credit | L8: Under 2k a month | M8: Occasional payments | N8: Unexplained signatories | O8: Digital, assisted | P8: Electronic, two sources | Q8: Comparison site | R8: Over 25k, consistent | S8: Up to 10 percent | T8: None | U8: Employer and retail | V8: Consistent | W8: No | X8: 2025-08-24
A9: NG-10104 | B9: Personal | C9: Individual | D9: Natural person | E9: Employed or pension | F9: No match | G9: No match | H9: United Kingdom | I9: Further tax residence, monitored | J9: UK only | K9: Current account, no overdraft | L9: Withdrawal only | M9: Not enabled | N9: Sole party | O9: Digital, own app | P9: Electronic, two sources | Q9: Direct | R9: 5k to 25k, consistent | S9: No cash credits | T9: None | U9: Sector 4 counterparties | V9: Consistent | W9: No | X9: 2025-02-15
A10: NG-10277 | B10: Personal | C10: Sole trader or joint | D10: Natural person | E10: Regulated profession | F10: No match | G10: No match | H10: United Kingdom | I10: UK tax residence only | J10: Unlisted countries | K10: Current account with credit | L10: Withdrawal only | M10: Occasional payments | N10: Sole party | O10: Digital, own app | P10: Electronic, two sources | Q10: Customer referral | R10: Under 5k, consistent | S10: No cash credits | T10: Up to 10 percent | U10: Many individuals | V10: Consistent | W10: No | X10: 2024-04-13
A11: NG-10052 | B11: Personal | C11: Individual | D11: Natural person | E11: Employed or pension | F11: No match | G11: No match | H11: United Kingdom | I11: UK tax residence only | J11: Weaker AML, unlisted | K11: Current account with credit | L11: Under 2k a month | M11: Enabled, unused | N11: Sole party | O11: Digital, own app | P11: Electronic, two sources | Q11: Direct | R11: Under 5k, consistent | S11: Up to 10 percent | T11: None | U11: Employer and retail | V11: Consistent | W11: No | X11: 2024-08-24
A12: NG-10107 | B12: Personal | C12: Individual | D12: Natural person | E12: Employed or pension | F12: No match | G12: No match | H12: United Kingdom | I12: UK tax residence only | J12: UK only | K12: Current account with credit | L12: Under 2k a month | M12: Not enabled | N12: Sole party | O12: Digital, own app | P12: Electronic, two sources | Q12: Customer referral | R12: Under 5k, consistent | S12: No cash credits | T12: None | U12: Employer and retail | V12: Consistent | W12: No | X12: 2024-11-08
... A401: NG-10037 | B401: Personal | C401: Individual | D401: Natural person | E401: General trade | F401: No match | G401: No match | H401: United Kingdom | I401: Further tax residence, unlisted | J401: UK only | K401: Savings only | L401: Withdrawal only | M401: Not enabled | N401: Sole party | O401: Telephone and branch | P401: Electronic, one source | Q401: Comparison site | R401: Under 5k, consistent | S401: No cash credits | T401: None | U401: Sector 4 counterparties | V401: Consistent | W401: No | X401: 2024-01-20

Sheet Scoring
A1: customer_id | B1: segment | C1: C1 | D1: C2 | E1: C3 | F1: C4 | G1: C5 | H1: G1 | I1: G2 | J1: G3 | K1: P1 | L1: P2 | M1: P3 | N1: P4 | O1: D1 | P1: D2 | Q1: D3 | R1: A1 | S1: A2 | T1: A3 | U1: A4 | V1: A5 | W1: Weighted score | X1: Rounded | Y1: Band | Z1: Escalator | AA1: Final rating | AB1: Customer | AC1: Geography | AD1: Product | AE1: Channel | AF1: Activity | AH1: Customer -10pp | AI1: Customer +10pp | AJ1: Geography -10pp | AK1: Geography +10pp | AL1: Product and service -10pp | AM1: Product and service +10pp | AN1: Delivery channel -10pp | AO1: Delivery channel +10pp | AP1: Expected activity -10pp | AQ1: Expected activity +10pp | AR1: Factors at 4+ | AS1: Rule B band | AT1: Rule C band | AU1: Rule D band | AV1: Rule D final
A2: =Customers!$A2 -> NG-10252 | B2: =Customers!$B2 -> Personal | C2: =INDEX(Mapping!$C$2:$C$99,MATCH(C$1&"|"&Customers!C2,Mapping!$D$2:$D$99,0)) -> 1 | D2: =INDEX(Mapping!$C$2:$C$99,MATCH(D$1&"|"&Customers!D2,Mapping!$D$2:$D$99,0)) -> 1 | E2: =INDEX(Mapping!$C$2:$C$99,MATCH(E$1&"|"&Customers!E2,Mapping!$D$2:$D$99,0)) -> 1 | F2: =INDEX(Mapping!$C$2:$C$99,MATCH(F$1&"|"&Customers!F2,Mapping!$D$2:$D$99,0)) -> 1 | G2: =INDEX(Mapping!$C$2:$C$99,MATCH(G$1&"|"&Customers!G2,Mapping!$D$2:$D$99,0)) -> 1 | H2: =INDEX(Mapping!$C$2:$C$99,MATCH(H$1&"|"&Customers!H2,Mapping!$D$2:$D$99,0)) -> 1 | I2: =INDEX(Mapping!$C$2:$C$99,MATCH(I$1&"|"&Customers!I2,Mapping!$D$2:$D$99,0)) -> 1 | J2: =INDEX(Mapping!$C$2:$C$99,MATCH(J$1&"|"&Customers!J2,Mapping!$D$2:$D$99,0)) -> 1 | ... V2: =INDEX(Mapping!$C$2:$C$99,MATCH(V$1&"|"&Customers!V2,Mapping!$D$2:$D$99,0)) -> 1 | W2: =SUMPRODUCT($C2:$V2,Weights!$C$27:$V$27) -> 1.49 | X2: =ROUND($W2,2) -> 1.49 | Y2: =IF($X2<=2,"Low",IF($X2<=3.49,"Medium","High")) -> Low | Z2: =IF(OR($F2>=3,$E2=5,$D2=5,$C2=5,$G2=5,$H2=5,$I2=5,$J2=5,Customers!$W2="Yes"),"Yes","No") -> No | AA2: =IF($Z2="Yes","High",$Y2) -> Low | AB2: =SUMPRODUCT($C2:$G2,Weights!$C$28:$G$28) -> 1 | AC2: =SUMPRODUCT($H2:$J2,Weights!$H$28:$J$28) -> 1 | AD2: =SUMPRODUCT($K2:$N2,Weights!$K$28:$N$28) -> 2.45 | AE2: =SUMPRODUCT($O2:$Q2,Weights!$O$28:$Q$28) -> 3 | AF2: =SUMPRODUCT($R2:$V2,Weights!$R$28:$V$28) -> 1 | AH2: =SUMPRODUCT($AB2:$AF2,Validation!$D$7:$H$7) -> 1.56 | AI2: =SUMPRODUCT($AB2:$AF2,Validation!$D$8:$H$8) -> 1.42 | AJ2: =SUMPRODUCT($AB2:$AF2,Validation!$D$9:$H$9) -> 1.5553333 | AK2: =SUMPRODUCT($AB2:$AF2,Validation!$D$10:$H$10) -> 1.4246667 | AL2: =SUMPRODUCT($AB2:$AF2,Validation!$D$11:$H$11) -> 1.37 | AM2: =SUMPRODUCT($AB2:$AF2,Validation!$D$12:$H$12) -> 1.61 | AN2: =SUMPRODUCT($AB2:$AF2,Validation!$D$13:$H$13) -> 1.3222222 | AO2: =SUMPRODUCT($AB2:$AF2,Validation!$D$14:$H$14) -> 1.6577778 | AP2: =SUMPRODUCT($AB2:$AF2,Validation!$D$15:$H$15) -> 1.5476471 | AQ2: =SUMPRODUCT($AB2:$AF2,Validation!$D$16:$H$16) -> 1.4323529 | AR2: =COUNTIF($C2:$V2,">=4") -> 0 | AS2: =IF($X2<=1.6,"Low",IF($X2<=2.2,"Medium","High")) -> Low | AT2: =IF($AR2=0,"Low",IF($AR2<3,"Medium","High")) -> Low | AU2: =IF(OR($AS2="High",$AT2="High"),"High",IF(OR($AS2="Medium",$AT2="Medium"),"Medium","Low")) -> Low | AV2: =IF($Z2="Yes","High",$AU2) -> Low
A3: =Customers!$A3 -> NG-10111 | B3: =Customers!$B3 -> Personal | C3: =INDEX(Mapping!$C$2:$C$99,MATCH(C$1&"|"&Customers!C3,Mapping!$D$2:$D$99,0)) -> 2 | D3: =INDEX(Mapping!$C$2:$C$99,MATCH(D$1&"|"&Customers!D3,Mapping!$D$2:$D$99,0)) -> 1 | E3: =INDEX(Mapping!$C$2:$C$99,MATCH(E$1&"|"&Customers!E3,Mapping!$D$2:$D$99,0)) -> 3 | F3: =INDEX(Mapping!$C$2:$C$99,MATCH(F$1&"|"&Customers!F3,Mapping!$D$2:$D$99,0)) -> 1 | G3: =INDEX(Mapping!$C$2:$C$99,MATCH(G$1&"|"&Customers!G3,Mapping!$D$2:$D$99,0)) -> 1 | H3: =INDEX(Mapping!$C$2:$C$99,MATCH(H$1&"|"&Customers!H3,Mapping!$D$2:$D$99,0)) -> 1 | I3: =INDEX(Mapping!$C$2:$C$99,MATCH(I$1&"|"&Customers!I3,Mapping!$D$2:$D$99,0)) -> 1 | J3: =INDEX(Mapping!$C$2:$C$99,MATCH(J$1&"|"&Customers!J3,Mapping!$D$2:$D$99,0)) -> 1 | ... V3: =INDEX(Mapping!$C$2:$C$99,MATCH(V$1&"|"&Customers!V3,Mapping!$D$2:$D$99,0)) -> 1 | W3: =SUMPRODUCT($C3:$V3,Weights!$C$27:$V$27) -> 1.5925 | X3: =ROUND($W3,2) -> 1.59 | Y3: =IF($X3<=2,"Low",IF($X3<=3.49,"Medium","High")) -> Low | Z3: =IF(OR($F3>=3,$E3=5,$D3=5,$C3=5,$G3=5,$H3=5,$I3=5,$J3=5,Customers!$W3="Yes"),"Yes","No") -> No | AA3: =IF($Z3="Yes","High",$Y3) -> Low | AB3: =SUMPRODUCT($C3:$G3,Weights!$C$28:$G$28) -> 1.7 | AC3: =SUMPRODUCT($H3:$J3,Weights!$H$28:$J$28) -> 1 | AD3: =SUMPRODUCT($K3:$N3,Weights!$K$28:$N$28) -> 1.85 | AE3: =SUMPRODUCT($O3:$Q3,Weights!$O$28:$Q$28) -> 1.4 | AF3: =SUMPRODUCT($R3:$V3,Weights!$R$28:$V$28) -> 2.15 | AH3: =SUMPRODUCT($AB3:$AF3,Validation!$D$7:$H$7) -> 1.5771429 | AI3: =SUMPRODUCT($AB3:$AF3,Validation!$D$8:$H$8) -> 1.6078571 | AJ3: =SUMPRODUCT($AB3:$AF3,Validation!$D$9:$H$9) -> 1.6715 | AK3: =SUMPRODUCT($AB3:$AF3,Validation!$D$10:$H$10) -> 1.5135 | AL3: =SUMPRODUCT($AB3:$AF3,Validation!$D$11:$H$11) -> 1.5603125 | AM3: =SUMPRODUCT($AB3:$AF3,Validation!$D$12:$H$12) -> 1.6246875 | AN3: =SUMPRODUCT($AB3:$AF3,Validation!$D$13:$H$13) -> 1.6138889 | AO3: =SUMPRODUCT($AB3:$AF3,Validation!$D$14:$H$14) -> 1.5711111 | AP3: =SUMPRODUCT($AB3:$AF3,Validation!$D$15:$H$15) -> 1.5269118 | AQ3: =SUMPRODUCT($AB3:$AF3,Validation!$D$16:$H$16) -> 1.6580882 | AR3: =COUNTIF($C3:$V3,">=4") -> 1 | AS3: =IF($X3<=1.6,"Low",IF($X3<=2.2,"Medium","High")) -> Low | AT3: =IF($AR3=0,"Low",IF($AR3<3,"Medium","High")) -> Medium | AU3: =IF(OR($AS3="High",$AT3="High"),"High",IF(OR($AS3="Medium",$AT3="Medium"),"Medium","Low")) -> Medium | AV3: =IF($Z3="Yes","High",$AU3) -> Medium
A4: =Customers!$A4 -> NG-10086 | B4: =Customers!$B4 -> Personal | C4: =INDEX(Mapping!$C$2:$C$99,MATCH(C$1&"|"&Customers!C4,Mapping!$D$2:$D$99,0)) -> 1 | D4: =INDEX(Mapping!$C$2:$C$99,MATCH(D$1&"|"&Customers!D4,Mapping!$D$2:$D$99,0)) -> 1 | E4: =INDEX(Mapping!$C$2:$C$99,MATCH(E$1&"|"&Customers!E4,Mapping!$D$2:$D$99,0)) -> 1 | F4: =INDEX(Mapping!$C$2:$C$99,MATCH(F$1&"|"&Customers!F4,Mapping!$D$2:$D$99,0)) -> 1 | G4: =INDEX(Mapping!$C$2:$C$99,MATCH(G$1&"|"&Customers!G4,Mapping!$D$2:$D$99,0)) -> 1 | H4: =INDEX(Mapping!$C$2:$C$99,MATCH(H$1&"|"&Customers!H4,Mapping!$D$2:$D$99,0)) -> 1 | I4: =INDEX(Mapping!$C$2:$C$99,MATCH(I$1&"|"&Customers!I4,Mapping!$D$2:$D$99,0)) -> 1 | J4: =INDEX(Mapping!$C$2:$C$99,MATCH(J$1&"|"&Customers!J4,Mapping!$D$2:$D$99,0)) -> 1 | ... V4: =INDEX(Mapping!$C$2:$C$99,MATCH(V$1&"|"&Customers!V4,Mapping!$D$2:$D$99,0)) -> 1 | W4: =SUMPRODUCT($C4:$V4,Weights!$C$27:$V$27) -> 1.46 | X4: =ROUND($W4,2) -> 1.46 | Y4: =IF($X4<=2,"Low",IF($X4<=3.49,"Medium","High")) -> Low | Z4: =IF(OR($F4>=3,$E4=5,$D4=5,$C4=5,$G4=5,$H4=5,$I4=5,$J4=5,Customers!$W4="Yes"),"Yes","No") -> No | AA4: =IF($Z4="Yes","High",$Y4) -> Low | AB4: =SUMPRODUCT($C4:$G4,Weights!$C$28:$G$28) -> 1 | AC4: =SUMPRODUCT($H4:$J4,Weights!$H$28:$J$28) -> 1 | AD4: =SUMPRODUCT($K4:$N4,Weights!$K$28:$N$28) -> 2.25 | AE4: =SUMPRODUCT($O4:$Q4,Weights!$O$28:$Q$28) -> 2.8 | AF4: =SUMPRODUCT($R4:$V4,Weights!$R$28:$V$28) -> 1.2 | AH4: =SUMPRODUCT($AB4:$AF4,Validation!$D$7:$H$7) -> 1.5257143 | AI4: =SUMPRODUCT($AB4:$AF4,Validation!$D$8:$H$8) -> 1.3942857 | AJ4: =SUMPRODUCT($AB4:$AF4,Validation!$D$9:$H$9) -> 1.5213333 | AK4: =SUMPRODUCT($AB4:$AF4,Validation!$D$10:$H$10) -> 1.3986667 | AL4: =SUMPRODUCT($AB4:$AF4,Validation!$D$11:$H$11) -> 1.36125 | AM4: =SUMPRODUCT($AB4:$AF4,Validation!$D$12:$H$12) -> 1.55875 | AN4: =SUMPRODUCT($AB4:$AF4,Validation!$D$13:$H$13) -> 1.3111111 | AO4: =SUMPRODUCT($AB4:$AF4,Validation!$D$14:$H$14) -> 1.6088889 | AP4: =SUMPRODUCT($AB4:$AF4,Validation!$D$15:$H$15) -> 1.4905882 | AQ4: =SUMPRODUCT($AB4:$AF4,Validation!$D$16:$H$16) -> 1.4294118 | AR4: =COUNTIF($C4:$V4,">=4") -> 0 | AS4: =IF($X4<=1.6,"Low",IF($X4<=2.2,"Medium","High")) -> Low | AT4: =IF($AR4=0,"Low",IF($AR4<3,"Medium","High")) -> Low | AU4: =IF(OR($AS4="High",$AT4="High"),"High",IF(OR($AS4="Medium",$AT4="Medium"),"Medium","Low")) -> Low | AV4: =IF($Z4="Yes","High",$AU4) -> Low
A5: =Customers!$A5 -> NG-10203 | B5: =Customers!$B5 -> Personal | C5: =INDEX(Mapping!$C$2:$C$99,MATCH(C$1&"|"&Customers!C5,Mapping!$D$2:$D$99,0)) -> 1 | D5: =INDEX(Mapping!$C$2:$C$99,MATCH(D$1&"|"&Customers!D5,Mapping!$D$2:$D$99,0)) -> 1 | E5: =INDEX(Mapping!$C$2:$C$99,MATCH(E$1&"|"&Customers!E5,Mapping!$D$2:$D$99,0)) -> 2 | F5: =INDEX(Mapping!$C$2:$C$99,MATCH(F$1&"|"&Customers!F5,Mapping!$D$2:$D$99,0)) -> 1 | G5: =INDEX(Mapping!$C$2:$C$99,MATCH(G$1&"|"&Customers!G5,Mapping!$D$2:$D$99,0)) -> 1 | H5: =INDEX(Mapping!$C$2:$C$99,MATCH(H$1&"|"&Customers!H5,Mapping!$D$2:$D$99,0)) -> 1 | I5: =INDEX(Mapping!$C$2:$C$99,MATCH(I$1&"|"&Customers!I5,Mapping!$D$2:$D$99,0)) -> 1 | J5: =INDEX(Mapping!$C$2:$C$99,MATCH(J$1&"|"&Customers!J5,Mapping!$D$2:$D$99,0)) -> 2 | ... V5: =INDEX(Mapping!$C$2:$C$99,MATCH(V$1&"|"&Customers!V5,Mapping!$D$2:$D$99,0)) -> 1 | W5: =SUMPRODUCT($C5:$V5,Weights!$C$27:$V$27) -> 1.61 | X5: =ROUND($W5,2) -> 1.61 | Y5: =IF($X5<=2,"Low",IF($X5<=3.49,"Medium","High")) -> Low | Z5: =IF(OR($F5>=3,$E5=5,$D5=5,$C5=5,$G5=5,$H5=5,$I5=5,$J5=5,Customers!$W5="Yes"),"Yes","No") -> No | AA5: =IF($Z5="Yes","High",$Y5) -> Low | AB5: =SUMPRODUCT($C5:$G5,Weights!$C$28:$G$28) -> 1.25 | AC5: =SUMPRODUCT($H5:$J5,Weights!$H$28:$J$28) -> 1.4 | AD5: =SUMPRODUCT($K5:$N5,Weights!$K$28:$N$28) -> 2.6 | AE5: =SUMPRODUCT($O5:$Q5,Weights!$O$28:$Q$28) -> 1.7 | AF5: =SUMPRODUCT($R5:$V5,Weights!$R$28:$V$28) -> 1.3 | AH5: =SUMPRODUCT($AB5:$AF5,Validation!$D$7:$H$7) -> 1.6614286 | AI5: =SUMPRODUCT($AB5:$AF5,Validation!$D$8:$H$8) -> 1.5585714 | AJ5: =SUMPRODUCT($AB5:$AF5,Validation!$D$9:$H$9) -> 1.638 | AK5: =SUMPRODUCT($AB5:$AF5,Validation!$D$10:$H$10) -> 1.582 | AL5: =SUMPRODUCT($AB5:$AF5,Validation!$D$11:$H$11) -> 1.48625 | AM5: =SUMPRODUCT($AB5:$AF5,Validation!$D$12:$H$12) -> 1.73375 | AN5: =SUMPRODUCT($AB5:$AF5,Validation!$D$13:$H$13) -> 1.6 | AO5: =SUMPRODUCT($AB5:$AF5,Validation!$D$14:$H$14) -> 1.62 | AP5: =SUMPRODUCT($AB5:$AF5,Validation!$D$15:$H$15) -> 1.6464706 | AQ5: =SUMPRODUCT($AB5:$AF5,Validation!$D$16:$H$16) -> 1.5735294 | AR5: =COUNTIF($C5:$V5,">=4") -> 0 | AS5: =IF($X5<=1.6,"Low",IF($X5<=2.2,"Medium","High")) -> Medium | AT5: =IF($AR5=0,"Low",IF($AR5<3,"Medium","High")) -> Low | AU5: =IF(OR($AS5="High",$AT5="High"),"High",IF(OR($AS5="Medium",$AT5="Medium"),"Medium","Low")) -> Medium | AV5: =IF($Z5="Yes","High",$AU5) -> Medium
A6: =Customers!$A6 -> NG-10171 | B6: =Customers!$B6 -> Personal | C6: =INDEX(Mapping!$C$2:$C$99,MATCH(C$1&"|"&Customers!C6,Mapping!$D$2:$D$99,0)) -> 1 | D6: =INDEX(Mapping!$C$2:$C$99,MATCH(D$1&"|"&Customers!D6,Mapping!$D$2:$D$99,0)) -> 1 | E6: =INDEX(Mapping!$C$2:$C$99,MATCH(E$1&"|"&Customers!E6,Mapping!$D$2:$D$99,0)) -> 1 | F6: =INDEX(Mapping!$C$2:$C$99,MATCH(F$1&"|"&Customers!F6,Mapping!$D$2:$D$99,0)) -> 1 | G6: =INDEX(Mapping!$C$2:$C$99,MATCH(G$1&"|"&Customers!G6,Mapping!$D$2:$D$99,0)) -> 1 | H6: =INDEX(Mapping!$C$2:$C$99,MATCH(H$1&"|"&Customers!H6,Mapping!$D$2:$D$99,0)) -> 1 | I6: =INDEX(Mapping!$C$2:$C$99,MATCH(I$1&"|"&Customers!I6,Mapping!$D$2:$D$99,0)) -> 1 | J6: =INDEX(Mapping!$C$2:$C$99,MATCH(J$1&"|"&Customers!J6,Mapping!$D$2:$D$99,0)) -> 1 | ... V6: =INDEX(Mapping!$C$2:$C$99,MATCH(V$1&"|"&Customers!V6,Mapping!$D$2:$D$99,0)) -> 1 | W6: =SUMPRODUCT($C6:$V6,Weights!$C$27:$V$27) -> 1.395 | X6: =ROUND($W6,2) -> 1.4 | Y6: =IF($X6<=2,"Low",IF($X6<=3.49,"Medium","High")) -> Low | Z6: =IF(OR($F6>=3,$E6=5,$D6=5,$C6=5,$G6=5,$H6=5,$I6=5,$J6=5,Customers!$W6="Yes"),"Yes","No") -> No | AA6: =IF($Z6="Yes","High",$Y6) -> Low | AB6: =SUMPRODUCT($C6:$G6,Weights!$C$28:$G$28) -> 1 | AC6: =SUMPRODUCT($H6:$J6,Weights!$H$28:$J$28) -> 1 | AD6: =SUMPRODUCT($K6:$N6,Weights!$K$28:$N$28) -> 2.1 | AE6: =SUMPRODUCT($O6:$Q6,Weights!$O$28:$Q$28) -> 2.3 | AF6: =SUMPRODUCT($R6:$V6,Weights!$R$28:$V$28) -> 1.3 | AH6: =SUMPRODUCT($AB6:$AF6,Validation!$D$7:$H$7) -> 1.4514286 | AI6: =SUMPRODUCT($AB6:$AF6,Validation!$D$8:$H$8) -> 1.3385714 | AJ6: =SUMPRODUCT($AB6:$AF6,Validation!$D$9:$H$9) -> 1.4476667 | AK6: =SUMPRODUCT($AB6:$AF6,Validation!$D$10:$H$10) -> 1.3423333 | AL6: =SUMPRODUCT($AB6:$AF6,Validation!$D$11:$H$11) -> 1.306875 | AM6: =SUMPRODUCT($AB6:$AF6,Validation!$D$12:$H$12) -> 1.483125 | AN6: =SUMPRODUCT($AB6:$AF6,Validation!$D$13:$H$13) -> 1.2944444 | AO6: =SUMPRODUCT($AB6:$AF6,Validation!$D$14:$H$14) -> 1.4955556 | AP6: =SUMPRODUCT($AB6:$AF6,Validation!$D$15:$H$15) -> 1.4061765 | AQ6: =SUMPRODUCT($AB6:$AF6,Validation!$D$16:$H$16) -> 1.3838235 | AR6: =COUNTIF($C6:$V6,">=4") -> 0 | AS6: =IF($X6<=1.6,"Low",IF($X6<=2.2,"Medium","High")) -> Low | AT6: =IF($AR6=0,"Low",IF($AR6<3,"Medium","High")) -> Low | AU6: =IF(OR($AS6="High",$AT6="High"),"High",IF(OR($AS6="Medium",$AT6="Medium"),"Medium","Low")) -> Low | AV6: =IF($Z6="Yes","High",$AU6) -> Low
A7: =Customers!$A7 -> NG-10124 | B7: =Customers!$B7 -> Personal | C7: =INDEX(Mapping!$C$2:$C$99,MATCH(C$1&"|"&Customers!C7,Mapping!$D$2:$D$99,0)) -> 1 | D7: =INDEX(Mapping!$C$2:$C$99,MATCH(D$1&"|"&Customers!D7,Mapping!$D$2:$D$99,0)) -> 1 | E7: =INDEX(Mapping!$C$2:$C$99,MATCH(E$1&"|"&Customers!E7,Mapping!$D$2:$D$99,0)) -> 1 | F7: =INDEX(Mapping!$C$2:$C$99,MATCH(F$1&"|"&Customers!F7,Mapping!$D$2:$D$99,0)) -> 1 | G7: =INDEX(Mapping!$C$2:$C$99,MATCH(G$1&"|"&Customers!G7,Mapping!$D$2:$D$99,0)) -> 1 | H7: =INDEX(Mapping!$C$2:$C$99,MATCH(H$1&"|"&Customers!H7,Mapping!$D$2:$D$99,0)) -> 1 | I7: =INDEX(Mapping!$C$2:$C$99,MATCH(I$1&"|"&Customers!I7,Mapping!$D$2:$D$99,0)) -> 1 | J7: =INDEX(Mapping!$C$2:$C$99,MATCH(J$1&"|"&Customers!J7,Mapping!$D$2:$D$99,0)) -> 1 | ... V7: =INDEX(Mapping!$C$2:$C$99,MATCH(V$1&"|"&Customers!V7,Mapping!$D$2:$D$99,0)) -> 1 | W7: =SUMPRODUCT($C7:$V7,Weights!$C$27:$V$27) -> 1.4 | X7: =ROUND($W7,2) -> 1.4 | Y7: =IF($X7<=2,"Low",IF($X7<=3.49,"Medium","High")) -> Low | Z7: =IF(OR($F7>=3,$E7=5,$D7=5,$C7=5,$G7=5,$H7=5,$I7=5,$J7=5,Customers!$W7="Yes"),"Yes","No") -> No | AA7: =IF($Z7="Yes","High",$Y7) -> Low | AB7: =SUMPRODUCT($C7:$G7,Weights!$C$28:$G$28) -> 1 | AC7: =SUMPRODUCT($H7:$J7,Weights!$H$28:$J$28) -> 1 | AD7: =SUMPRODUCT($K7:$N7,Weights!$K$28:$N$28) -> 2.2 | AE7: =SUMPRODUCT($O7:$Q7,Weights!$O$28:$Q$28) -> 2.6 | AF7: =SUMPRODUCT($R7:$V7,Weights!$R$28:$V$28) -> 1 | AH7: =SUMPRODUCT($AB7:$AF7,Validation!$D$7:$H$7) -> 1.4571429 | AI7: =SUMPRODUCT($AB7:$AF7,Validation!$D$8:$H$8) -> 1.3428571 | AJ7: =SUMPRODUCT($AB7:$AF7,Validation!$D$9:$H$9) -> 1.4533333 | AK7: =SUMPRODUCT($AB7:$AF7,Validation!$D$10:$H$10) -> 1.3466667 | AL7: =SUMPRODUCT($AB7:$AF7,Validation!$D$11:$H$11) -> 1.3 | AM7: =SUMPRODUCT($AB7:$AF7,Validation!$D$12:$H$12) -> 1.5 | AN7: =SUMPRODUCT($AB7:$AF7,Validation!$D$13:$H$13) -> 1.2666667 | AO7: =SUMPRODUCT($AB7:$AF7,Validation!$D$14:$H$14) -> 1.5333333 | AP7: =SUMPRODUCT($AB7:$AF7,Validation!$D$15:$H$15) -> 1.4470588 | AQ7: =SUMPRODUCT($AB7:$AF7,Validation!$D$16:$H$16) -> 1.3529412 | AR7: =COUNTIF($C7:$V7,">=4") -> 0 | AS7: =IF($X7<=1.6,"Low",IF($X7<=2.2,"Medium","High")) -> Low | AT7: =IF($AR7=0,"Low",IF($AR7<3,"Medium","High")) -> Low | AU7: =IF(OR($AS7="High",$AT7="High"),"High",IF(OR($AS7="Medium",$AT7="Medium"),"Medium","Low")) -> Low | AV7: =IF($Z7="Yes","High",$AU7) -> Low
A8: =Customers!$A8 -> NG-10062 | B8: =Customers!$B8 -> Personal | C8: =INDEX(Mapping!$C$2:$C$99,MATCH(C$1&"|"&Customers!C8,Mapping!$D$2:$D$99,0)) -> 1 | D8: =INDEX(Mapping!$C$2:$C$99,MATCH(D$1&"|"&Customers!D8,Mapping!$D$2:$D$99,0)) -> 1 | E8: =INDEX(Mapping!$C$2:$C$99,MATCH(E$1&"|"&Customers!E8,Mapping!$D$2:$D$99,0)) -> 3 | F8: =INDEX(Mapping!$C$2:$C$99,MATCH(F$1&"|"&Customers!F8,Mapping!$D$2:$D$99,0)) -> 1 | G8: =INDEX(Mapping!$C$2:$C$99,MATCH(G$1&"|"&Customers!G8,Mapping!$D$2:$D$99,0)) -> 1 | H8: =INDEX(Mapping!$C$2:$C$99,MATCH(H$1&"|"&Customers!H8,Mapping!$D$2:$D$99,0)) -> 1 | I8: =INDEX(Mapping!$C$2:$C$99,MATCH(I$1&"|"&Customers!I8,Mapping!$D$2:$D$99,0)) -> 1 | J8: =INDEX(Mapping!$C$2:$C$99,MATCH(J$1&"|"&Customers!J8,Mapping!$D$2:$D$99,0)) -> 1 | ... V8: =INDEX(Mapping!$C$2:$C$99,MATCH(V$1&"|"&Customers!V8,Mapping!$D$2:$D$99,0)) -> 1 | W8: =SUMPRODUCT($C8:$V8,Weights!$C$27:$V$27) -> 1.975 | X8: =ROUND($W8,2) -> 1.98 | Y8: =IF($X8<=2,"Low",IF($X8<=3.49,"Medium","High")) -> Low | Z8: =IF(OR($F8>=3,$E8=5,$D8=5,$C8=5,$G8=5,$H8=5,$I8=5,$J8=5,Customers!$W8="Yes"),"Yes","No") -> No | AA8: =IF($Z8="Yes","High",$Y8) -> Low | AB8: =SUMPRODUCT($C8:$G8,Weights!$C$28:$G$28) -> 1.5 | AC8: =SUMPRODUCT($H8:$J8,Weights!$H$28:$J$28) -> 1 | AD8: =SUMPRODUCT($K8:$N8,Weights!$K$28:$N$28) -> 3.3 | AE8: =SUMPRODUCT($O8:$Q8,Weights!$O$28:$Q$28) -> 3.45 | AF8: =SUMPRODUCT($R8:$V8,Weights!$R$28:$V$28) -> 1.8 | AH8: =SUMPRODUCT($AB8:$AF8,Validation!$D$7:$H$7) -> 2.0428571 | AI8: =SUMPRODUCT($AB8:$AF8,Validation!$D$8:$H$8) -> 1.9071429 | AJ8: =SUMPRODUCT($AB8:$AF8,Validation!$D$9:$H$9) -> 2.105 | AK8: =SUMPRODUCT($AB8:$AF8,Validation!$D$10:$H$10) -> 1.845 | AL8: =SUMPRODUCT($AB8:$AF8,Validation!$D$11:$H$11) -> 1.809375 | AM8: =SUMPRODUCT($AB8:$AF8,Validation!$D$12:$H$12) -> 2.140625 | AN8: =SUMPRODUCT($AB8:$AF8,Validation!$D$13:$H$13) -> 1.8111111 | AO8: =SUMPRODUCT($AB8:$AF8,Validation!$D$14:$H$14) -> 2.1388889 | AP8: =SUMPRODUCT($AB8:$AF8,Validation!$D$15:$H$15) -> 1.9955882 | AQ8: =SUMPRODUCT($AB8:$AF8,Validation!$D$16:$H$16) -> 1.9544118 | AR8: =COUNTIF($C8:$V8,">=4") -> 2 | AS8: =IF($X8<=1.6,"Low",IF($X8<=2.2,"Medium","High")) -> Medium | AT8: =IF($AR8=0,"Low",IF($AR8<3,"Medium","High")) -> Medium | AU8: =IF(OR($AS8="High",$AT8="High"),"High",IF(OR($AS8="Medium",$AT8="Medium"),"Medium","Low")) -> Medium | AV8: =IF($Z8="Yes","High",$AU8) -> Medium
A9: =Customers!$A9 -> NG-10104 | B9: =Customers!$B9 -> Personal | C9: =INDEX(Mapping!$C$2:$C$99,MATCH(C$1&"|"&Customers!C9,Mapping!$D$2:$D$99,0)) -> 1 | D9: =INDEX(Mapping!$C$2:$C$99,MATCH(D$1&"|"&Customers!D9,Mapping!$D$2:$D$99,0)) -> 1 | E9: =INDEX(Mapping!$C$2:$C$99,MATCH(E$1&"|"&Customers!E9,Mapping!$D$2:$D$99,0)) -> 1 | F9: =INDEX(Mapping!$C$2:$C$99,MATCH(F$1&"|"&Customers!F9,Mapping!$D$2:$D$99,0)) -> 1 | G9: =INDEX(Mapping!$C$2:$C$99,MATCH(G$1&"|"&Customers!G9,Mapping!$D$2:$D$99,0)) -> 1 | H9: =INDEX(Mapping!$C$2:$C$99,MATCH(H$1&"|"&Customers!H9,Mapping!$D$2:$D$99,0)) -> 1 | I9: =INDEX(Mapping!$C$2:$C$99,MATCH(I$1&"|"&Customers!I9,Mapping!$D$2:$D$99,0)) -> 4 | J9: =INDEX(Mapping!$C$2:$C$99,MATCH(J$1&"|"&Customers!J9,Mapping!$D$2:$D$99,0)) -> 1 | ... V9: =INDEX(Mapping!$C$2:$C$99,MATCH(V$1&"|"&Customers!V9,Mapping!$D$2:$D$99,0)) -> 1 | W9: =SUMPRODUCT($C9:$V9,Weights!$C$27:$V$27) -> 1.535 | X9: =ROUND($W9,2) -> 1.54 | Y9: =IF($X9<=2,"Low",IF($X9<=3.49,"Medium","High")) -> Low | Z9: =IF(OR($F9>=3,$E9=5,$D9=5,$C9=5,$G9=5,$H9=5,$I9=5,$J9=5,Customers!$W9="Yes"),"Yes","No") -> No | AA9: =IF($Z9="Yes","High",$Y9) -> Low | AB9: =SUMPRODUCT($C9:$G9,Weights!$C$28:$G$28) -> 1 | AC9: =SUMPRODUCT($H9:$J9,Weights!$H$28:$J$28) -> 1.6 | AD9: =SUMPRODUCT($K9:$N9,Weights!$K$28:$N$28) -> 1.6 | AE9: =SUMPRODUCT($O9:$Q9,Weights!$O$28:$Q$28) -> 2.6 | AF9: =SUMPRODUCT($R9:$V9,Weights!$R$28:$V$28) -> 1.7 | AH9: =SUMPRODUCT($AB9:$AF9,Validation!$D$7:$H$7) -> 1.6114286 | AI9: =SUMPRODUCT($AB9:$AF9,Validation!$D$8:$H$8) -> 1.4585714 | AJ9: =SUMPRODUCT($AB9:$AF9,Validation!$D$9:$H$9) -> 1.5263333 | AK9: =SUMPRODUCT($AB9:$AF9,Validation!$D$10:$H$10) -> 1.5436667 | AL9: =SUMPRODUCT($AB9:$AF9,Validation!$D$11:$H$11) -> 1.526875 | AM9: =SUMPRODUCT($AB9:$AF9,Validation!$D$12:$H$12) -> 1.543125 | AN9: =SUMPRODUCT($AB9:$AF9,Validation!$D$13:$H$13) -> 1.4166667 | AO9: =SUMPRODUCT($AB9:$AF9,Validation!$D$14:$H$14) -> 1.6533333 | AP9: =SUMPRODUCT($AB9:$AF9,Validation!$D$15:$H$15) -> 1.5155882 | AQ9: =SUMPRODUCT($AB9:$AF9,Validation!$D$16:$H$16) -> 1.5544118 | AR9: =COUNTIF($C9:$V9,">=4") -> 2 | AS9: =IF($X9<=1.6,"Low",IF($X9<=2.2,"Medium","High")) -> Low | AT9: =IF($AR9=0,"Low",IF($AR9<3,"Medium","High")) -> Medium | AU9: =IF(OR($AS9="High",$AT9="High"),"High",IF(OR($AS9="Medium",$AT9="Medium"),"Medium","Low")) -> Medium | AV9: =IF($Z9="Yes","High",$AU9) -> Medium
A10: =Customers!$A10 -> NG-10277 | B10: =Customers!$B10 -> Personal | C10: =INDEX(Mapping!$C$2:$C$99,MATCH(C$1&"|"&Customers!C10,Mapping!$D$2:$D$99,0)) -> 2 | D10: =INDEX(Mapping!$C$2:$C$99,MATCH(D$1&"|"&Customers!D10,Mapping!$D$2:$D$99,0)) -> 1 | E10: =INDEX(Mapping!$C$2:$C$99,MATCH(E$1&"|"&Customers!E10,Mapping!$D$2:$D$99,0)) -> 2 | F10: =INDEX(Mapping!$C$2:$C$99,MATCH(F$1&"|"&Customers!F10,Mapping!$D$2:$D$99,0)) -> 1 | G10: =INDEX(Mapping!$C$2:$C$99,MATCH(G$1&"|"&Customers!G10,Mapping!$D$2:$D$99,0)) -> 1 | H10: =INDEX(Mapping!$C$2:$C$99,MATCH(H$1&"|"&Customers!H10,Mapping!$D$2:$D$99,0)) -> 1 | I10: =INDEX(Mapping!$C$2:$C$99,MATCH(I$1&"|"&Customers!I10,Mapping!$D$2:$D$99,0)) -> 1 | J10: =INDEX(Mapping!$C$2:$C$99,MATCH(J$1&"|"&Customers!J10,Mapping!$D$2:$D$99,0)) -> 2 | ... V10: =INDEX(Mapping!$C$2:$C$99,MATCH(V$1&"|"&Customers!V10,Mapping!$D$2:$D$99,0)) -> 1 | W10: =SUMPRODUCT($C10:$V10,Weights!$C$27:$V$27) -> 1.78 | X10: =ROUND($W10,2) -> 1.78 | Y10: =IF($X10<=2,"Low",IF($X10<=3.49,"Medium","High")) -> Low | Z10: =IF(OR($F10>=3,$E10=5,$D10=5,$C10=5,$G10=5,$H10=5,$I10=5,$J10=5,Customers!$W10="Yes"),"Yes","No") -> No | AA10: =IF($Z10="Yes","High",$Y10) -> Low | AB10: =SUMPRODUCT($C10:$G10,Weights!$C$28:$G$28) -> 1.45 | AC10: =SUMPRODUCT($H10:$J10,Weights!$H$28:$J$28) -> 1.4 | AD10: =SUMPRODUCT($K10:$N10,Weights!$K$28:$N$28) -> 2.45 | AE10: =SUMPRODUCT($O10:$Q10,Weights!$O$28:$Q$28) -> 2.8 | AF10: =SUMPRODUCT($R10:$V10,Weights!$R$28:$V$28) -> 1.5 | AH10: =SUMPRODUCT($AB10:$AF10,Validation!$D$7:$H$7) -> 1.8271429 | AI10: =SUMPRODUCT($AB10:$AF10,Validation!$D$8:$H$8) -> 1.7328571 | AJ10: =SUMPRODUCT($AB10:$AF10,Validation!$D$9:$H$9) -> 1.8306667 | AK10: =SUMPRODUCT($AB10:$AF10,Validation!$D$10:$H$10) -> 1.7293333 | AL10: =SUMPRODUCT($AB10:$AF10,Validation!$D$11:$H$11) -> 1.69625 | AM10: =SUMPRODUCT($AB10:$AF10,Validation!$D$12:$H$12) -> 1.86375 | AN10: =SUMPRODUCT($AB10:$AF10,Validation!$D$13:$H$13) -> 1.6666667 | AO10: =SUMPRODUCT($AB10:$AF10,Validation!$D$14:$H$14) -> 1.8933333 | AP10: =SUMPRODUCT($AB10:$AF10,Validation!$D$15:$H$15) -> 1.8129412 | AQ10: =SUMPRODUCT($AB10:$AF10,Validation!$D$16:$H$16) -> 1.7470588 | AR10: =COUNTIF($C10:$V10,">=4") -> 0 | AS10: =IF($X10<=1.6,"Low",IF($X10<=2.2,"Medium","High")) -> Medium | AT10: =IF($AR10=0,"Low",IF($AR10<3,"Medium","High")) -> Low | AU10: =IF(OR($AS10="High",$AT10="High"),"High",IF(OR($AS10="Medium",$AT10="Medium"),"Medium","Low")) -> Medium | AV10: =IF($Z10="Yes","High",$AU10) -> Medium
A11: =Customers!$A11 -> NG-10052 | B11: =Customers!$B11 -> Personal | C11: =INDEX(Mapping!$C$2:$C$99,MATCH(C$1&"|"&Customers!C11,Mapping!$D$2:$D$99,0)) -> 1 | D11: =INDEX(Mapping!$C$2:$C$99,MATCH(D$1&"|"&Customers!D11,Mapping!$D$2:$D$99,0)) -> 1 | E11: =INDEX(Mapping!$C$2:$C$99,MATCH(E$1&"|"&Customers!E11,Mapping!$D$2:$D$99,0)) -> 1 | F11: =INDEX(Mapping!$C$2:$C$99,MATCH(F$1&"|"&Customers!F11,Mapping!$D$2:$D$99,0)) -> 1 | G11: =INDEX(Mapping!$C$2:$C$99,MATCH(G$1&"|"&Customers!G11,Mapping!$D$2:$D$99,0)) -> 1 | H11: =INDEX(Mapping!$C$2:$C$99,MATCH(H$1&"|"&Customers!H11,Mapping!$D$2:$D$99,0)) -> 1 | I11: =INDEX(Mapping!$C$2:$C$99,MATCH(I$1&"|"&Customers!I11,Mapping!$D$2:$D$99,0)) -> 1 | J11: =INDEX(Mapping!$C$2:$C$99,MATCH(J$1&"|"&Customers!J11,Mapping!$D$2:$D$99,0)) -> 3 | ... V11: =INDEX(Mapping!$C$2:$C$99,MATCH(V$1&"|"&Customers!V11,Mapping!$D$2:$D$99,0)) -> 1 | W11: =SUMPRODUCT($C11:$V11,Weights!$C$27:$V$27) -> 1.695 | X11: =ROUND($W11,2) -> 1.7 | Y11: =IF($X11<=2,"Low",IF($X11<=3.49,"Medium","High")) -> Low | Z11: =IF(OR($F11>=3,$E11=5,$D11=5,$C11=5,$G11=5,$H11=5,$I11=5,$J11=5,Customers!$W11="Yes"),"Yes","No") -> No | AA11: =IF($Z11="Yes","High",$Y11) -> Low | AB11: =SUMPRODUCT($C11:$G11,Weights!$C$28:$G$28) -> 1 | AC11: =SUMPRODUCT($H11:$J11,Weights!$H$28:$J$28) -> 1.8 | AD11: =SUMPRODUCT($K11:$N11,Weights!$K$28:$N$28) -> 2.45 | AE11: =SUMPRODUCT($O11:$Q11,Weights!$O$28:$Q$28) -> 2.6 | AF11: =SUMPRODUCT($R11:$V11,Weights!$R$28:$V$28) -> 1.3 | AH11: =SUMPRODUCT($AB11:$AF11,Validation!$D$7:$H$7) -> 1.7942857 | AI11: =SUMPRODUCT($AB11:$AF11,Validation!$D$8:$H$8) -> 1.5957143 | AJ11: =SUMPRODUCT($AB11:$AF11,Validation!$D$9:$H$9) -> 1.681 | AK11: =SUMPRODUCT($AB11:$AF11,Validation!$D$10:$H$10) -> 1.709 | AL11: =SUMPRODUCT($AB11:$AF11,Validation!$D$11:$H$11) -> 1.600625 | AM11: =SUMPRODUCT($AB11:$AF11,Validation!$D$12:$H$12) -> 1.789375 | AN11: =SUMPRODUCT($AB11:$AF11,Validation!$D$13:$H$13) -> 1.5944444 | AO11: =SUMPRODUCT($AB11:$AF11,Validation!$D$14:$H$14) -> 1.7955556 | AP11: =SUMPRODUCT($AB11:$AF11,Validation!$D$15:$H$15) -> 1.7414706 | AQ11: =SUMPRODUCT($AB11:$AF11,Validation!$D$16:$H$16) -> 1.6485294 | AR11: =COUNTIF($C11:$V11,">=4") -> 0 | AS11: =IF($X11<=1.6,"Low",IF($X11<=2.2,"Medium","High")) -> Medium | AT11: =IF($AR11=0,"Low",IF($AR11<3,"Medium","High")) -> Low | AU11: =IF(OR($AS11="High",$AT11="High"),"High",IF(OR($AS11="Medium",$AT11="Medium"),"Medium","Low")) -> Medium | AV11: =IF($Z11="Yes","High",$AU11) -> Medium
A12: =Customers!$A12 -> NG-10107 | B12: =Customers!$B12 -> Personal | C12: =INDEX(Mapping!$C$2:$C$99,MATCH(C$1&"|"&Customers!C12,Mapping!$D$2:$D$99,0)) -> 1 | D12: =INDEX(Mapping!$C$2:$C$99,MATCH(D$1&"|"&Customers!D12,Mapping!$D$2:$D$99,0)) -> 1 | E12: =INDEX(Mapping!$C$2:$C$99,MATCH(E$1&"|"&Customers!E12,Mapping!$D$2:$D$99,0)) -> 1 | F12: =INDEX(Mapping!$C$2:$C$99,MATCH(F$1&"|"&Customers!F12,Mapping!$D$2:$D$99,0)) -> 1 | G12: =INDEX(Mapping!$C$2:$C$99,MATCH(G$1&"|"&Customers!G12,Mapping!$D$2:$D$99,0)) -> 1 | H12: =INDEX(Mapping!$C$2:$C$99,MATCH(H$1&"|"&Customers!H12,Mapping!$D$2:$D$99,0)) -> 1 | I12: =INDEX(Mapping!$C$2:$C$99,MATCH(I$1&"|"&Customers!I12,Mapping!$D$2:$D$99,0)) -> 1 | J12: =INDEX(Mapping!$C$2:$C$99,MATCH(J$1&"|"&Customers!J12,Mapping!$D$2:$D$99,0)) -> 1 | ... V12: =INDEX(Mapping!$C$2:$C$99,MATCH(V$1&"|"&Customers!V12,Mapping!$D$2:$D$99,0)) -> 1 | W12: =SUMPRODUCT($C12:$V12,Weights!$C$27:$V$27) -> 1.42 | X12: =ROUND($W12,2) -> 1.42 | Y12: =IF($X12<=2,"Low",IF($X12<=3.49,"Medium","High")) -> Low | Z12: =IF(OR($F12>=3,$E12=5,$D12=5,$C12=5,$G12=5,$H12=5,$I12=5,$J12=5,Customers!$W12="Yes"),"Yes","No") -> No | AA12: =IF($Z12="Yes","High",$Y12) -> Low | AB12: =SUMPRODUCT($C12:$G12,Weights!$C$28:$G$28) -> 1 | AC12: =SUMPRODUCT($H12:$J12,Weights!$H$28:$J$28) -> 1 | AD12: =SUMPRODUCT($K12:$N12,Weights!$K$28:$N$28) -> 2.2 | AE12: =SUMPRODUCT($O12:$Q12,Weights!$O$28:$Q$28) -> 2.8 | AF12: =SUMPRODUCT($R12:$V12,Weights!$R$28:$V$28) -> 1 | AH12: =SUMPRODUCT($AB12:$AF12,Validation!$D$7:$H$7) -> 1.48 | AI12: =SUMPRODUCT($AB12:$AF12,Validation!$D$8:$H$8) -> 1.36 | AJ12: =SUMPRODUCT($AB12:$AF12,Validation!$D$9:$H$9) -> 1.476 | AK12: =SUMPRODUCT($AB12:$AF12,Validation!$D$10:$H$10) -> 1.364 | AL12: =SUMPRODUCT($AB12:$AF12,Validation!$D$11:$H$11) -> 1.3225 | AM12: =SUMPRODUCT($AB12:$AF12,Validation!$D$12:$H$12) -> 1.5175 | AN12: =SUMPRODUCT($AB12:$AF12,Validation!$D$13:$H$13) -> 1.2666667 | AO12: =SUMPRODUCT($AB12:$AF12,Validation!$D$14:$H$14) -> 1.5733333 | AP12: =SUMPRODUCT($AB12:$AF12,Validation!$D$15:$H$15) -> 1.4694118 | AQ12: =SUMPRODUCT($AB12:$AF12,Validation!$D$16:$H$16) -> 1.3705882 | AR12: =COUNTIF($C12:$V12,">=4") -> 0 | AS12: =IF($X12<=1.6,"Low",IF($X12<=2.2,"Medium","High")) -> Low | AT12: =IF($AR12=0,"Low",IF($AR12<3,"Medium","High")) -> Low | AU12: =IF(OR($AS12="High",$AT12="High"),"High",IF(OR($AS12="Medium",$AT12="Medium"),"Medium","Low")) -> Low | AV12: =IF($Z12="Yes","High",$AU12) -> Low
A13: =Customers!$A13 -> NG-10190 | B13: =Customers!$B13 -> Personal | C13: =INDEX(Mapping!$C$2:$C$99,MATCH(C$1&"|"&Customers!C13,Mapping!$D$2:$D$99,0)) -> 1 | D13: =INDEX(Mapping!$C$2:$C$99,MATCH(D$1&"|"&Customers!D13,Mapping!$D$2:$D$99,0)) -> 1 | E13: =INDEX(Mapping!$C$2:$C$99,MATCH(E$1&"|"&Customers!E13,Mapping!$D$2:$D$99,0)) -> 1 | F13: =INDEX(Mapping!$C$2:$C$99,MATCH(F$1&"|"&Customers!F13,Mapping!$D$2:$D$99,0)) -> 1 | G13: =INDEX(Mapping!$C$2:$C$99,MATCH(G$1&"|"&Customers!G13,Mapping!$D$2:$D$99,0)) -> 1 | H13: =INDEX(Mapping!$C$2:$C$99,MATCH(H$1&"|"&Customers!H13,Mapping!$D$2:$D$99,0)) -> 1 | I13: =INDEX(Mapping!$C$2:$C$99,MATCH(I$1&"|"&Customers!I13,Mapping!$D$2:$D$99,0)) -> 1 | J13: =INDEX(Mapping!$C$2:$C$99,MATCH(J$1&"|"&Customers!J13,Mapping!$D$2:$D$99,0)) -> 1 | ... V13: =INDEX(Mapping!$C$2:$C$99,MATCH(V$1&"|"&Customers!V13,Mapping!$D$2:$D$99,0)) -> 1 | W13: =SUMPRODUCT($C13:$V13,Weights!$C$27:$V$27) -> 1.515 | X13: =ROUND($W13,2) -> 1.52 | Y13: =IF($X13<=2,"Low",IF($X13<=3.49,"Medium","High")) -> Low | Z13: =IF(OR($F13>=3,$E13=5,$D13=5,$C13=5,$G13=5,$H13=5,$I13=5,$J13=5,Customers!$W13="Yes"),"Yes","No") -> No | AA13: =IF($Z13="Yes","High",$Y13) -> Low | AB13: =SUMPRODUCT($C13:$G13,Weights!$C$28:$G$28) -> 1 | AC13: =SUMPRODUCT($H13:$J13,Weights!$H$28:$J$28) -> 1 | AD13: =SUMPRODUCT($K13:$N13,Weights!$K$28:$N$28) -> 2.35 | AE13: =SUMPRODUCT($O13:$Q13,Weights!$O$28:$Q$28) -> 3 | AF13: =SUMPRODUCT($R13:$V13,Weights!$R$28:$V$28) -> 1.3 | AH13: =SUMPRODUCT($AB13:$AF13,Validation!$D$7:$H$7) -> 1.5885714 | AI13: =SUMPRODUCT($AB13:$AF13,Validation!$D$8:$H$8) -> 1.4414286 | AJ13: =SUMPRODUCT($AB13:$AF13,Validation!$D$9:$H$9) -> 1.5836667 | AK13: =SUMPRODUCT($AB13:$AF13,Validation!$D$10:$H$10) -> 1.4463333 | AL13: =SUMPRODUCT($AB13:$AF13,Validation!$D$11:$H$11) -> 1.410625 | AM13: =SUMPRODUCT($AB13:$AF13,Validation!$D$12:$H$12) -> 1.619375 | AN13: =SUMPRODUCT($AB13:$AF13,Validation!$D$13:$H$13) -> 1.35 | AO13: =SUMPRODUCT($AB13:$AF13,Validation!$D$14:$H$14) -> 1.68 | AP13: =SUMPRODUCT($AB13:$AF13,Validation!$D$15:$H$15) -> 1.5402941 | AQ13: =SUMPRODUCT($AB13:$AF13,Validation!$D$16:$H$16) -> 1.4897059 | AR13: =COUNTIF($C13:$V13,">=4") -> 0 | AS13: =IF($X13<=1.6,"Low",IF($X13<=2.2,"Medium","High")) -> Low | AT13: =IF($AR13=0,"Low",IF($AR13<3,"Medium","High")) -> Low | AU13: =IF(OR($AS13="High",$AT13="High"),"High",IF(OR($AS13="Medium",$AT13="Medium"),"Medium","Low")) -> Low | AV13: =IF($Z13="Yes","High",$AU13) -> Low
... A401: =Customers!$A401 -> NG-10037 | B401: =Customers!$B401 -> Personal | C401: =INDEX(Mapping!$C$2:$C$99,MATCH(C$1&"|"&Customers!C401,Mapping!$D$2:$D$99,0)) -> 1 | D401: =INDEX(Mapping!$C$2:$C$99,MATCH(D$1&"|"&Customers!D401,Mapping!$D$2:$D$99,0)) -> 1 | E401: =INDEX(Mapping!$C$2:$C$99,MATCH(E$1&"|"&Customers!E401,Mapping!$D$2:$D$99,0)) -> 3 | F401: =INDEX(Mapping!$C$2:$C$99,MATCH(F$1&"|"&Customers!F401,Mapping!$D$2:$D$99,0)) -> 1 | G401: =INDEX(Mapping!$C$2:$C$99,MATCH(G$1&"|"&Customers!G401,Mapping!$D$2:$D$99,0)) -> 1 | H401: =INDEX(Mapping!$C$2:$C$99,MATCH(H$1&"|"&Customers!H401,Mapping!$D$2:$D$99,0)) -> 1 | I401: =INDEX(Mapping!$C$2:$C$99,MATCH(I$1&"|"&Customers!I401,Mapping!$D$2:$D$99,0)) -> 2 | J401: =INDEX(Mapping!$C$2:$C$99,MATCH(J$1&"|"&Customers!J401,Mapping!$D$2:$D$99,0)) -> 1 | ... V401: =INDEX(Mapping!$C$2:$C$99,MATCH(V$1&"|"&Customers!V401,Mapping!$D$2:$D$99,0)) -> 1 | W401: =SUMPRODUCT($C401:$V401,Weights!$C$27:$V$27) -> 1.5075 | X401: =ROUND($W401,2) -> 1.51 | Y401: =IF($X401<=2,"Low",IF($X401<=3.49,"Medium","High")) -> Low | Z401: =IF(OR($F401>=3,$E401=5,$D401=5,$C401=5,$G401=5,$H401=5,$I401=5,$J401=5,Customers!$W401="Yes"),"Yes","No") -> No | AA401: =IF($Z401="Yes","High",$Y401) -> Low | AB401: =SUMPRODUCT($C401:$G401,Weights!$C$28:$G$28) -> 1.5 | AC401: =SUMPRODUCT($H401:$J401,Weights!$H$28:$J$28) -> 1.2 | AD401: =SUMPRODUCT($K401:$N401,Weights!$K$28:$N$28) -> 1.25 | AE401: =SUMPRODUCT($O401:$Q401,Weights!$O$28:$Q$28) -> 2.9 | AF401: =SUMPRODUCT($R401:$V401,Weights!$R$28:$V$28) -> 1.45 | AH401: =SUMPRODUCT($AB401:$AF401,Validation!$D$7:$H$7) -> 1.5085714 | AI401: =SUMPRODUCT($AB401:$AF401,Validation!$D$8:$H$8) -> 1.5064286 | AJ401: =SUMPRODUCT($AB401:$AF401,Validation!$D$9:$H$9) -> 1.5485 | AK401: =SUMPRODUCT($AB401:$AF401,Validation!$D$10:$H$10) -> 1.4665 | AL401: =SUMPRODUCT($AB401:$AF401,Validation!$D$11:$H$11) -> 1.5396875 | AM401: =SUMPRODUCT($AB401:$AF401,Validation!$D$12:$H$12) -> 1.4753125 | AN401: =SUMPRODUCT($AB401:$AF401,Validation!$D$13:$H$13) -> 1.3527778 | AO401: =SUMPRODUCT($AB401:$AF401,Validation!$D$14:$H$14) -> 1.6622222 | AP401: =SUMPRODUCT($AB401:$AF401,Validation!$D$15:$H$15) -> 1.5142647 | AQ401: =SUMPRODUCT($AB401:$AF401,Validation!$D$16:$H$16) -> 1.5007353 | AR401: =COUNTIF($C401:$V401,">=4") -> 2 | AS401: =IF($X401<=1.6,"Low",IF($X401<=2.2,"Medium","High")) -> Low | AT401: =IF($AR401=0,"Low",IF($AR401<3,"Medium","High")) -> Medium | AU401: =IF(OR($AS401="High",$AT401="High"),"High",IF(OR($AS401="Medium",$AT401="Medium"),"Medium","Low")) -> Medium | AV401: =IF($Z401="Yes","High",$AU401) -> Medium

Sheet Dashboard
B1: Population of 400 customers, scored
B2: Everything on this sheet is calculated from the Scoring sheet. Nothing is typed in.
B4: Final customer risk rating
B5: Rating | C5: Customers | D5: Share
B6: Low | C6: =COUNTIF(Scoring!$AA$2:$AA$401,$B6) -> 295 | D6: =$C6/400 -> 0.7375
B7: Medium | C7: =COUNTIF(Scoring!$AA$2:$AA$401,$B7) -> 62 | D7: =$C7/400 -> 0.155
B8: High | C8: =COUNTIF(Scoring!$AA$2:$AA$401,$B8) -> 43 | D8: =$C8/400 -> 0.1075
B9: Total | C9: =SUM($C$6:$C$8) -> 400
B11: Band from the arithmetic alone, before escalators
B12: Band | C12: Customers | D12: Share
B13: Low | C13: =COUNTIF(Scoring!$Y$2:$Y$401,$B13) -> 313 | D13: =$C13/400 -> 0.7825
B14: Medium | C14: =COUNTIF(Scoring!$Y$2:$Y$401,$B14) -> 87 | D14: =$C14/400 -> 0.2175
B15: High | C15: =COUNTIF(Scoring!$Y$2:$Y$401,$B15) -> 0 | D15: =$C15/400 -> 0
B16: Lifted to High by an escalator | C16: =COUNTIFS(Scoring!$Y$2:$Y$401,"<>High",Scoring!$AA$2:$AA$401,"High") -> 43
B19: Why customers were escalated
B20: Escalator | C20: Customers
B21: 5.3(a) PEP, family member or close associate | C21: =COUNTIF(Scoring!$F$2:$F$401,">=3") -> 11
B22: 5.3(b) Call for action jurisdiction | C22: =SUMPRODUCT(--((Scoring!$H$2:$H$401=5)+(Scoring!$I$2:$I$401=5)+(Scoring!$J$2:$J$401=5)>0)) -> 5
B23: 5.3(c) MSB, TCSP or high-value dealer | C23: =COUNTIF(Scoring!$E$2:$E$401,5) -> 12
B24: 5.3(d) Opaque ownership structure | C24: =SUMPRODUCT(--((Scoring!$D$2:$D$401=5)+(Scoring!$C$2:$C$401=5)>0)) -> 5
B25: 5.3(e) Adverse media, financial crime | C25: =COUNTIF(Scoring!$G$2:$G$401,5) -> 2
B26: 5.3(f) SAR in the preceding 12 months | C26: =COUNTIF(Customers!$W$2:$W$401,"Yes") -> 11
B27: Any escalator (customers, not reasons) | C27: =COUNTIF(Scoring!$Z$2:$Z$401,"Yes") -> 43
B28: Escalated by 5.3(f) and by nothing else | C28: =SUMPRODUCT((Customers!$W$2:$W$401="Yes")*--((Scoring!$F$2:$F$401>=3)+(Scoring!$E$2:$E$401=5)+(Scoring!$D$2:$D$401=5)+(Scoring!$C$2:$C$401=5)+(Scoring!$G$2:$G$401=5)+(Scoring!$H$2:$H$401=5)+(Scoring!$I$2:$I$401=5)+(Scoring!$J$2:$J$401=5)=0)) -> 11
B31: Rating by segment
B32: Segment | C32: Low | D32: Medium | E32: High | F32: Total
B33: Personal | C33: =COUNTIFS(Scoring!$B$2:$B$401,$B33,Scoring!$AA$2:$AA$401,"Low") -> 280 | D33: =COUNTIFS(Scoring!$B$2:$B$401,$B33,Scoring!$AA$2:$AA$401,"Medium") -> 0 | E33: =COUNTIFS(Scoring!$B$2:$B$401,$B33,Scoring!$AA$2:$AA$401,"High") -> 20 | F33: =SUM($C33:$E33) -> 300
B34: Sole trader | C34: =COUNTIFS(Scoring!$B$2:$B$401,$B34,Scoring!$AA$2:$AA$401,"Low") -> 15 | D34: =COUNTIFS(Scoring!$B$2:$B$401,$B34,Scoring!$AA$2:$AA$401,"Medium") -> 36 | E34: =COUNTIFS(Scoring!$B$2:$B$401,$B34,Scoring!$AA$2:$AA$401,"High") -> 9 | F34: =SUM($C34:$E34) -> 60
B35: Limited company | C35: =COUNTIFS(Scoring!$B$2:$B$401,$B35,Scoring!$AA$2:$AA$401,"Low") -> 0 | D35: =COUNTIFS(Scoring!$B$2:$B$401,$B35,Scoring!$AA$2:$AA$401,"Medium") -> 26 | E35: =COUNTIFS(Scoring!$B$2:$B$401,$B35,Scoring!$AA$2:$AA$401,"High") -> 14 | F35: =SUM($C35:$E35) -> 40
B38: How much work each category is doing
B39: Category | C39: Mean | D39: Lowest | E39: Highest | F39: Std dev | G39: At the minimum
B40: Customer | C40: =AVERAGE(Scoring!$AB$2:$AB$401) -> 1.4625 | D40: =MIN(Scoring!$AB$2:$AB$401) -> 1 | E40: =MAX(Scoring!$AB$2:$AB$401) -> 3.3 | F40: =STDEV(Scoring!$AB$2:$AB$401) -> 0.48588472 | G40: =SUMPRODUCT(--(Scoring!$AB$2:$AB$401=MIN(Scoring!$AB$2:$AB$401)))/400 -> 0.3325
B41: Geography | C41: =AVERAGE(Scoring!$AC$2:$AC$401) -> 1.1605 | D41: =MIN(Scoring!$AC$2:$AC$401) -> 1 | E41: =MAX(Scoring!$AC$2:$AC$401) -> 2.8 | F41: =STDEV(Scoring!$AC$2:$AC$401) -> 0.30227168 | G41: =SUMPRODUCT(--(Scoring!$AC$2:$AC$401=MIN(Scoring!$AC$2:$AC$401)))/400 -> 0.695
B42: Product and service | C42: =AVERAGE(Scoring!$AD$2:$AD$401) -> 2.423625 | D42: =MIN(Scoring!$AD$2:$AD$401) -> 1.25 | E42: =MAX(Scoring!$AD$2:$AD$401) -> 4.45 | F42: =STDEV(Scoring!$AD$2:$AD$401) -> 0.68930106 | G42: =SUMPRODUCT(--(Scoring!$AD$2:$AD$401=MIN(Scoring!$AD$2:$AD$401)))/400 -> 0.0175
B43: Delivery channel | C43: =AVERAGE(Scoring!$AE$2:$AE$401) -> 2.66675 | D43: =MIN(Scoring!$AE$2:$AE$401) -> 1 | E43: =MAX(Scoring!$AE$2:$AE$401) -> 4.2 | F43: =STDEV(Scoring!$AE$2:$AE$401) -> 0.53844149 | G43: =SUMPRODUCT(--(Scoring!$AE$2:$AE$401=MIN(Scoring!$AE$2:$AE$401)))/400 -> 0.01
B44: Expected activity | C44: =AVERAGE(Scoring!$AF$2:$AF$401) -> 1.75775 | D44: =MIN(Scoring!$AF$2:$AF$401) -> 1 | E44: =MAX(Scoring!$AF$2:$AF$401) -> 3.45 | F44: =STDEV(Scoring!$AF$2:$AF$401) -> 0.53105554 | G44: =SUMPRODUCT(--(Scoring!$AF$2:$AF$401=MIN(Scoring!$AF$2:$AF$401)))/400 -> 0.065
B45: Standard deviation is the measure that matters. A category whose score barely varies across the population is not separating customers, whatever weight it carries.
B48: Overall score
B49: Statistic | C49: Value
B50: Mean | C50: =AVERAGE(Scoring!$W$2:$W$401) -> 1.7439375
B51: Lowest | C51: =MIN(Scoring!$W$2:$W$401) -> 1.185
B52: Highest | C52: =MAX(Scoring!$W$2:$W$401) -> 2.7625
B53: Standard deviation | C53: =STDEV(Scoring!$W$2:$W$401) -> 0.32731889
B54: Within 0.10 of the Low/Medium boundary | C54: =COUNTIFS(Scoring!$X$2:$X$401,">=1.91",Scoring!$X$2:$X$401,"<=2.10") -> 37
B57: Distribution of the overall score
B58: From | C58: To | D58: Customers
B59: 1 | C59: 1.25 | D59: =COUNTIFS(Scoring!$W$2:$W$401,">=1.00",Scoring!$W$2:$W$401,"<1.25") -> 1
B60: 1.25 | C60: 1.5 | D60: =COUNTIFS(Scoring!$W$2:$W$401,">=1.25",Scoring!$W$2:$W$401,"<1.50") -> 95
B61: 1.5 | C61: 1.75 | D61: =COUNTIFS(Scoring!$W$2:$W$401,">=1.50",Scoring!$W$2:$W$401,"<1.75") -> 161
B62: 1.75 | C62: 2 | D62: =COUNTIFS(Scoring!$W$2:$W$401,">=1.75",Scoring!$W$2:$W$401,"<2.00") -> 55
B63: 2 | C63: 2.25 | D63: =COUNTIFS(Scoring!$W$2:$W$401,">=2.00",Scoring!$W$2:$W$401,"<2.25") -> 49
B64: 2.25 | C64: 2.5 | D64: =COUNTIFS(Scoring!$W$2:$W$401,">=2.25",Scoring!$W$2:$W$401,"<2.50") -> 26
B65: 2.5 | C65: 2.75 | D65: =COUNTIFS(Scoring!$W$2:$W$401,">=2.50",Scoring!$W$2:$W$401,"<2.75") -> 12
B66: 2.75 | C66: 3 | D66: =COUNTIFS(Scoring!$W$2:$W$401,">=2.75",Scoring!$W$2:$W$401,"<3.00") -> 1
B67: 3 | C67: 3.25 | D67: =COUNTIFS(Scoring!$W$2:$W$401,">=3.00",Scoring!$W$2:$W$401,"<3.25") -> 0
B68: 3.25 | C68: 3.5 | D68: =COUNTIFS(Scoring!$W$2:$W$401,">=3.25",Scoring!$W$2:$W$401,"<3.50") -> 0
B69: 3.5 | C69: 3.75 | D69: =COUNTIFS(Scoring!$W$2:$W$401,">=3.50",Scoring!$W$2:$W$401,"<3.75") -> 0
B70: 3.75 | C70: 4 | D70: =COUNTIFS(Scoring!$W$2:$W$401,">=3.75",Scoring!$W$2:$W$401,"<4.00") -> 0
B71: 4 | C71: 4.25 | D71: =COUNTIFS(Scoring!$W$2:$W$401,">=4.00",Scoring!$W$2:$W$401,"<4.25") -> 0
B72: 4.25 | C72: 4.5 | D72: =COUNTIFS(Scoring!$W$2:$W$401,">=4.25",Scoring!$W$2:$W$401,"<4.50") -> 0
B73: 4.5 | C73: 4.75 | D73: =COUNTIFS(Scoring!$W$2:$W$401,">=4.50",Scoring!$W$2:$W$401,"<4.75") -> 0
B74: 4.75 | C74: 5 | D74: =COUNTIFS(Scoring!$W$2:$W$401,">=4.75",Scoring!$W$2:$W$401,"<5.00") -> 0

Sheet Checks
A1: Integrity checks
A2: Every row must read OK. These recalculate whenever the population or a weight changes.
A4: # | B4: What is tested | C4: Result | D4: Expected | E4: Status
A5: 1 | B5: The population contains 400 customers | C5: =COUNTA(Scoring!$A$2:$A$401) -> 400 | D5: 400 | E5: =IF($C5=$D5,"OK","CHECK") -> OK
A6: 2 | B6: Every recorded level resolves to a score in the library | C6: =SUMPRODUCT(--ISNA(Scoring!$C$2:$V$401)) -> 0 | D6: 0 | E6: =IF($C6=$D6,"OK","CHECK") -> OK
A7: 3 | B7: No factor score falls outside the range 1 to 5 | C7: =SUMPRODUCT(--((Scoring!$C$2:$V$401<1)+(Scoring!$C$2:$V$401>5)>0)) -> 0 | D7: 0 | E7: =IF($C7=$D7,"OK","CHECK") -> OK
A8: 4 | B8: Effective weights still sum to 100% | C8: =ROUND(SUM(Weights!$C$2:$C$21),6) -> 1 | D8: 1 | E8: =IF($C8=$D8,"OK","CHECK") -> OK
A9: 5 | B9: Weights inside the five categories sum to 100% each | C9: =ROUND(SUM(Weights!$D$2:$D$21),6) -> 5 | D9: 5 | E9: =IF($C9=$D9,"OK","CHECK") -> OK
A10: 6 | B10: No overall score below 1.00 | C10: =SUMPRODUCT(--(Scoring!$W$2:$W$401<1)) -> 0 | D10: 0 | E10: =IF($C10=$D10,"OK","CHECK") -> OK
A11: 7 | B11: No overall score above 5.00 | C11: =SUMPRODUCT(--(Scoring!$W$2:$W$401>5)) -> 0 | D11: 0 | E11: =IF($C11=$D11,"OK","CHECK") -> OK
A12: 8 | B12: Where no escalator applies, the final rating equals the band | C12: =SUMPRODUCT(--(Scoring!$Z$2:$Z$401="No"),--(Scoring!$AA$2:$AA$401<>Scoring!$Y$2:$Y$401)) -> 0 | D12: 0 | E12: =IF($C12=$D12,"OK","CHECK") -> OK
A13: 9 | B13: Every escalated customer is rated High | C13: =SUMPRODUCT(--(Scoring!$Z$2:$Z$401="Yes"),--(Scoring!$AA$2:$AA$401<>"High")) -> 0 | D13: 0 | E13: =IF($C13=$D13,"OK","CHECK") -> OK
A14: 10 | B14: No duplicate customer reference | C14: =SUMPRODUCT(--(COUNTIF(Scoring!$A$2:$A$401,Scoring!$A$2:$A$401)>1)) -> 0 | D14: 0 | E14: =IF($C14=$D14,"OK","CHECK") -> OK
A15: 11 | B15: The five category scores reconstruct the overall score | C15: =SUMPRODUCT(--(ROUND(Scoring!$AB$2:$AB$401*Weights!$H$2+Scoring!$AC$2:$AC$401*Weights!$H$3+Scoring!$AD$2:$AD$401*Weights!$H$4+Scoring!$AE$2:$AE$401*Weights!$H$5+Scoring!$AF$2:$AF$401*Weights!$H$6,6)<>ROUND(Scoring!$W$2:$W$401,6))) -> 0 | D15: 0 | E15: =IF($C15=$D15,"OK","CHECK") -> OK
A16: 12 | B16: No duplicate lookup key in the mapping table | C16: =SUMPRODUCT(--(COUNTIF(Mapping!$D$2:$D$99,Mapping!$D$2:$D$99)>1)) -> 0 | D16: 0 | E16: =IF($C16=$D16,"OK","CHECK") -> OK
A17: 13 | B17: Every backtest level resolves to a score in the library | C17: =SUMPRODUCT(--ISNA(Backtest!$W$4:$AP$16)) -> 0 | D17: 0 | E17: =IF($C17=$D17,"OK","CHECK") -> OK
A18: 14 | B18: The backtest uses the same weights as the population | C18: =ROUND(SUMPRODUCT(Backtest!$W$4:$AP$4,Weights!$C$27:$V$27)-Backtest!$AQ$4,9) -> 0 | D18: 0 | E18: =IF($C18=$D18,"OK","CHECK") -> OK
A19: 15 | B19: The FO-lo and FO-mid rows differ in exactly one factor score | C19: =SUMPRODUCT(--(Backtest!$W$4:$AP$4<>Backtest!$W$5:$AP$5)) -> 1 | D19: 1 | E19: =IF($C19=$D19,"OK","CHECK") -> OK
A20: 16 | B20: The FO-hi row scores at or above FO-lo on every factor | C20: =SUMPRODUCT(--(Backtest!$W$4:$AP$4>Backtest!$W$6:$AP$6)) -> 0 | D20: 0 | E20: =IF($C20=$D20,"OK","CHECK") -> OK
A21: 17 | B21: Every sensitivity scenario still sums to 100% | C21: =SUMPRODUCT(--(ROUND(MMULT(Validation!$D$7:$H$16,{1;1;1;1;1}),6)<>1)) -> 0 | D21: 0 | E21: =IF($C21=$D21,"OK","CHECK") -> OK
A22: 18 | B22: Rule D is never softer than rule B or rule C | C22: =SUMPRODUCT(--((Scoring!$AS$2:$AS$401="High")+(Scoring!$AT$2:$AT$401="High")>0),--(Scoring!$AU$2:$AU$401<>"High")) -> 0 | D22: 0 | E22: =IF($C22=$D22,"OK","CHECK") -> OK
A23: 19 | B23: Every customer has a factor-severity count between 0 and 20 | C23: =SUMPRODUCT(--((Scoring!$AR$2:$AR$401<0)+(Scoring!$AR$2:$AR$401>20)>0)) -> 0 | D23: 0 | E23: =IF($C23=$D23,"OK","CHECK") -> OK
B25: Overall status | E25: =IF(COUNTIF($E$5:$E$23,"CHECK")=0,"ALL OK","FIX") -> ALL OK

Sheet Validation
B1: Step 5: model validation
B2: Everything on this sheet is calculated from the Scoring sheet. The weights in columns D to H are the only typed numbers, and they are the sensitivity scenarios themselves.
B5: 1. Weight sensitivity
B6: Scenario | C6: Effect | D6: C | E6: G | F6: P | G6: D | H6: A | I6: Band changes, current bands | J6: Band changes, rebanded
B7: Customer -10pp | C7: Customer at 20% | D7: 0.2 | E7: 0.28571429 | F7: 0.22857143 | G7: 0.11428571 | H7: 0.17142857 | I7: =SUMPRODUCT(--((1+(ROUND(Scoring!$AH$2:$AH$401,2)>2)+(ROUND(Scoring!$AH$2:$AH$401,2)>3.49))<>(1+(Scoring!$X$2:$X$401>2)+(Scoring!$X$2:$X$401>3.49)))) -> 15 | J7: =SUMPRODUCT(--((1+(ROUND(Scoring!$AH$2:$AH$401,2)>1.6)+(ROUND(Scoring!$AH$2:$AH$401,2)>2.2))<>(1+(Scoring!$X$2:$X$401>1.6)+(Scoring!$X$2:$X$401>2.2)))) -> 54
B8: Customer +10pp | C8: Customer at 40% | D8: 0.4 | E8: 0.21428571 | F8: 0.17142857 | G8: 0.085714286 | H8: 0.12857143 | I8: =SUMPRODUCT(--((1+(ROUND(Scoring!$AI$2:$AI$401,2)>2)+(ROUND(Scoring!$AI$2:$AI$401,2)>3.49))<>(1+(Scoring!$X$2:$X$401>2)+(Scoring!$X$2:$X$401>3.49)))) -> 4 | J8: =SUMPRODUCT(--((1+(ROUND(Scoring!$AI$2:$AI$401,2)>1.6)+(ROUND(Scoring!$AI$2:$AI$401,2)>2.2))<>(1+(Scoring!$X$2:$X$401>1.6)+(Scoring!$X$2:$X$401>2.2)))) -> 47
B9: Geography -10pp | C9: Geography at 15% | D9: 0.34 | E9: 0.15 | F9: 0.22666667 | G9: 0.11333333 | H9: 0.17 | I9: =SUMPRODUCT(--((1+(ROUND(Scoring!$AJ$2:$AJ$401,2)>2)+(ROUND(Scoring!$AJ$2:$AJ$401,2)>3.49))<>(1+(Scoring!$X$2:$X$401>2)+(Scoring!$X$2:$X$401>3.49)))) -> 16 | J9: =SUMPRODUCT(--((1+(ROUND(Scoring!$AJ$2:$AJ$401,2)>1.6)+(ROUND(Scoring!$AJ$2:$AJ$401,2)>2.2))<>(1+(Scoring!$X$2:$X$401>1.6)+(Scoring!$X$2:$X$401>2.2)))) -> 67
B10: Geography +10pp | C10: Geography at 35% | D10: 0.26 | E10: 0.35 | F10: 0.17333333 | G10: 0.086666667 | H10: 0.13 | I10: =SUMPRODUCT(--((1+(ROUND(Scoring!$AK$2:$AK$401,2)>2)+(ROUND(Scoring!$AK$2:$AK$401,2)>3.49))<>(1+(Scoring!$X$2:$X$401>2)+(Scoring!$X$2:$X$401>3.49)))) -> 26 | J10: =SUMPRODUCT(--((1+(ROUND(Scoring!$AK$2:$AK$401,2)>1.6)+(ROUND(Scoring!$AK$2:$AK$401,2)>2.2))<>(1+(Scoring!$X$2:$X$401>1.6)+(Scoring!$X$2:$X$401>2.2)))) -> 68
B11: Product and service -10pp | C11: Product and service at 10% | D11: 0.3375 | E11: 0.28125 | F11: 0.1 | G11: 0.1125 | H11: 0.16875 | I11: =SUMPRODUCT(--((1+(ROUND(Scoring!$AL$2:$AL$401,2)>2)+(ROUND(Scoring!$AL$2:$AL$401,2)>3.49))<>(1+(Scoring!$X$2:$X$401>2)+(Scoring!$X$2:$X$401>3.49)))) -> 24 | J11: =SUMPRODUCT(--((1+(ROUND(Scoring!$AL$2:$AL$401,2)>1.6)+(ROUND(Scoring!$AL$2:$AL$401,2)>2.2))<>(1+(Scoring!$X$2:$X$401>1.6)+(Scoring!$X$2:$X$401>2.2)))) -> 69
B12: Product and service +10pp | C12: Product and service at 30% | D12: 0.2625 | E12: 0.21875 | F12: 0.3 | G12: 0.0875 | H12: 0.13125 | I12: =SUMPRODUCT(--((1+(ROUND(Scoring!$AM$2:$AM$401,2)>2)+(ROUND(Scoring!$AM$2:$AM$401,2)>3.49))<>(1+(Scoring!$X$2:$X$401>2)+(Scoring!$X$2:$X$401>3.49)))) -> 20 | J12: =SUMPRODUCT(--((1+(ROUND(Scoring!$AM$2:$AM$401,2)>1.6)+(ROUND(Scoring!$AM$2:$AM$401,2)>2.2))<>(1+(Scoring!$X$2:$X$401>1.6)+(Scoring!$X$2:$X$401>2.2)))) -> 80
B13: Delivery channel -10pp | C13: Delivery channel at 0% | D13: 0.33333333 | E13: 0.27777778 | F13: 0.22222222 | G13: 0 | H13: 0.16666667 | I13: =SUMPRODUCT(--((1+(ROUND(Scoring!$AN$2:$AN$401,2)>2)+(ROUND(Scoring!$AN$2:$AN$401,2)>3.49))<>(1+(Scoring!$X$2:$X$401>2)+(Scoring!$X$2:$X$401>3.49)))) -> 14 | J13: =SUMPRODUCT(--((1+(ROUND(Scoring!$AN$2:$AN$401,2)>1.6)+(ROUND(Scoring!$AN$2:$AN$401,2)>2.2))<>(1+(Scoring!$X$2:$X$401>1.6)+(Scoring!$X$2:$X$401>2.2)))) -> 83
B14: Delivery channel +10pp | C14: Delivery channel at 20% | D14: 0.26666667 | E14: 0.22222222 | F14: 0.17777778 | G14: 0.2 | H14: 0.13333333 | I14: =SUMPRODUCT(--((1+(ROUND(Scoring!$AO$2:$AO$401,2)>2)+(ROUND(Scoring!$AO$2:$AO$401,2)>3.49))<>(1+(Scoring!$X$2:$X$401>2)+(Scoring!$X$2:$X$401>3.49)))) -> 25 | J14: =SUMPRODUCT(--((1+(ROUND(Scoring!$AO$2:$AO$401,2)>1.6)+(ROUND(Scoring!$AO$2:$AO$401,2)>2.2))<>(1+(Scoring!$X$2:$X$401>1.6)+(Scoring!$X$2:$X$401>2.2)))) -> 100
B15: Expected activity -10pp | C15: Expected activity at 5% | D15: 0.33529412 | E15: 0.27941176 | F15: 0.22352941 | G15: 0.11176471 | H15: 0.05 | I15: =SUMPRODUCT(--((1+(ROUND(Scoring!$AP$2:$AP$401,2)>2)+(ROUND(Scoring!$AP$2:$AP$401,2)>3.49))<>(1+(Scoring!$X$2:$X$401>2)+(Scoring!$X$2:$X$401>3.49)))) -> 9 | J15: =SUMPRODUCT(--((1+(ROUND(Scoring!$AP$2:$AP$401,2)>1.6)+(ROUND(Scoring!$AP$2:$AP$401,2)>2.2))<>(1+(Scoring!$X$2:$X$401>1.6)+(Scoring!$X$2:$X$401>2.2)))) -> 29
B16: Expected activity +10pp | C16: Expected activity at 25% | D16: 0.26470588 | E16: 0.22058824 | F16: 0.17647059 | G16: 0.088235294 | H16: 0.25 | I16: =SUMPRODUCT(--((1+(ROUND(Scoring!$AQ$2:$AQ$401,2)>2)+(ROUND(Scoring!$AQ$2:$AQ$401,2)>3.49))<>(1+(Scoring!$X$2:$X$401>2)+(Scoring!$X$2:$X$401>3.49)))) -> 7 | J16: =SUMPRODUCT(--((1+(ROUND(Scoring!$AQ$2:$AQ$401,2)>1.6)+(ROUND(Scoring!$AQ$2:$AQ$401,2)>2.2))<>(1+(Scoring!$X$2:$X$401>1.6)+(Scoring!$X$2:$X$401>2.2)))) -> 36
B18: Out of 400 customers. Read the two right-hand columns together: the same weight change moves far more customers once the band boundaries sit where the population actually is.
B21: 2. Aggregation rules compared
B22: Rule | C22: Definition | D22: Low | E22: Medium | F22: High | G22: High share
B23: A current | C23: Weighted average, bands 1.00 / 2.01 / 3.50 | D23: =COUNTIF(Scoring!$AA$2:$AA$401,"Low") -> 295 | E23: =COUNTIF(Scoring!$AA$2:$AA$401,"Medium") -> 62 | F23: =COUNTIF(Scoring!$AA$2:$AA$401,"High") -> 43 | G23: =$F23/400 -> 0.1075
B24: B rebanded | C24: Weighted average, bands 1.00 / 1.61 / 2.21 | D24: =SUMPRODUCT(--(IF(Scoring!$Z$2:$Z$401="Yes","High",Scoring!$AS$2:$AS$401)="Low")) -> 165 | E24: =SUMPRODUCT(--(IF(Scoring!$Z$2:$Z$401="Yes","High",Scoring!$AS$2:$AS$401)="Medium")) -> 161 | F24: =SUMPRODUCT(--(IF(Scoring!$Z$2:$Z$401="Yes","High",Scoring!$AS$2:$AS$401)="High")) -> 74 | G24: =$F24/400 -> 0.185
B25: C severity | C25: Count of factors scoring 4 or 5: 0 Low, 1-2 Medium, 3+ High | D25: =SUMPRODUCT(--(IF(Scoring!$Z$2:$Z$401="Yes","High",Scoring!$AT$2:$AT$401)="Low")) -> 120 | E25: =SUMPRODUCT(--(IF(Scoring!$Z$2:$Z$401="Yes","High",Scoring!$AT$2:$AT$401)="Medium")) -> 155 | F25: =SUMPRODUCT(--(IF(Scoring!$Z$2:$Z$401="Yes","High",Scoring!$AT$2:$AT$401)="High")) -> 125 | G25: =$F25/400 -> 0.3125
B26: D higher of B and C | C26: The worse of the two ratings above | D26: =COUNTIF(Scoring!$AV$2:$AV$401,"Low") -> 91 | E26: =COUNTIF(Scoring!$AV$2:$AV$401,"Medium") -> 182 | F26: =COUNTIF(Scoring!$AV$2:$AV$401,"High") -> 127 | G26: =$F26/400 -> 0.3175
B28: The High column is the operational question. Rules C and D put roughly 1.7 times as many customers into High as rule B does. The judgement that this is unaffordable is an assumption about cost, not a sourced constraint: docs/04-model-validation.md section 4.2 says so, and names what would settle it.
B31: 3. The 2026 change to jurisdiction-based enhanced due diligence
B32: Measure | C32: Customers | D32: Share of the book
B33: Touching a FATF increased-monitoring jurisdiction | C33: =SUMPRODUCT(--((Scoring!$H$2:$H$401=4)+(Scoring!$I$2:$I$401=4)+(Scoring!$J$2:$J$401=4)>0)) -> 11 | D33: =$C33/400 -> 0.0275
B34: Touching a FATF call-for-action jurisdiction | C34: =SUMPRODUCT(--((Scoring!$H$2:$H$401=5)+(Scoring!$I$2:$I$401=5)+(Scoring!$J$2:$J$401=5)>0)) -> 5 | D34: =$C34/400 -> 0.0125
B35: Mandatory jurisdiction-based EDD before 2026 | C35: =SUMPRODUCT(--(((Scoring!$H$2:$H$401=4)+(Scoring!$I$2:$I$401=4)+(Scoring!$J$2:$J$401=4)>0)+((Scoring!$H$2:$H$401=5)+(Scoring!$I$2:$I$401=5)+(Scoring!$J$2:$J$401=5)>0)>0)) -> 16 | D35: =$C35/400 -> 0.04
B36: Mandatory jurisdiction-based EDD under the 2026 rule | C36: =SUMPRODUCT(--((Scoring!$H$2:$H$401=5)+(Scoring!$I$2:$I$401=5)+(Scoring!$J$2:$J$401=5)>0)) -> 5 | D36: =$C36/400 -> 0.0125
B37: Customers losing automatic EDD | C37: =SUMPRODUCT(--(((Scoring!$H$2:$H$401=4)+(Scoring!$I$2:$I$401=4)+(Scoring!$J$2:$J$401=4)>0))*--(NOT(((Scoring!$H$2:$H$401=5)+(Scoring!$I$2:$I$401=5)+(Scoring!$J$2:$J$401=5)>0)))) -> 11 | D37: =$C37/400 -> 0.0275
B38: Of those, escalated for some other reason | C38: =SUMPRODUCT(--(((Scoring!$H$2:$H$401=4)+(Scoring!$I$2:$I$401=4)+(Scoring!$J$2:$J$401=4)>0)),--(NOT(((Scoring!$H$2:$H$401=5)+(Scoring!$I$2:$I$401=5)+(Scoring!$J$2:$J$401=5)>0))),--(Scoring!$Z$2:$Z$401="Yes")) -> 0 | D38: =$C38/400 -> 0
B39: Of those, rated Low once EDD is no longer automatic | C39: =SUMPRODUCT(--(((Scoring!$H$2:$H$401=4)+(Scoring!$I$2:$I$401=4)+(Scoring!$J$2:$J$401=4)>0)),--(NOT(((Scoring!$H$2:$H$401=5)+(Scoring!$I$2:$I$401=5)+(Scoring!$J$2:$J$401=5)>0))),--(Scoring!$AA$2:$AA$401="Low")) -> 9 | D39: =$C39/400 -> 0.0225

Sheet Backtest
A1: Step 4: enforcement cases, scored at onboarding
A2: Each case is reconstructed as it looked on the day the bank took it on, using only what that bank knew or recorded then, and is scored twice: -lo is the reading most favourable to the customer that the published notice permits, -hi the least favourable reading a competent analyst could have defended on the same information. Where the notice settles a factor, both rows carry the same level. FO-lo and FO-mid hold the entire file constant and change only the C3 reading. Two cases are labelled -a and -b instead, because their pair is not a favourable/adverse bracket: Stunt & Co is dated (the application file of 16 January 2015, then the same file after the meeting of 27 January 2015), and Santander is conditional (the file as recorded, then the same file with the business verified as a money service business, which is the verification the FCA found was missing). Same Mapping, same Weights and same rules as the 400 synthetic customers.
A3: Case | B3: Enforcement case | C3: C1 level | D3: C2 level | E3: C3 level | F3: C4 level | G3: C5 level | H3: G1 level | I3: G2 level | J3: G3 level | K3: P1 level | L3: P2 level | M3: P3 level | N3: P4 level | O3: D1 level | P3: D2 level | Q3: D3 level | R3: A1 level | S3: A2 level | T3: A3 level | U3: A4 level | V3: A5 level | W3: C1 | X3: C2 | Y3: C3 | Z3: C4 | AA3: C5 | AB3: G1 | AC3: G2 | AD3: G3 | AE3: P1 | AF3: P2 | AG3: P3 | AH3: P4 | AI3: D1 | AJ3: D2 | AK3: D3 | AL3: A1 | AM3: A2 | AN3: A3 | AO3: A4 | AP3: A5 | AQ3: Weighted score | AR3: Rounded | AS3: Band | AT3: Escalator | AU3: Final rating | AV3: Customer | AW3: Geography | AX3: Product | AY3: Channel | AZ3: Activity | BA3: Rule B band | BB3: Recommended final
A4: FO-lo | B4: NatWest / Fowler Oldfield, favourable reading, cash-intensive trade | C4: UK company, natural owners | D4: One or two UBOs | E4: Cash-intensive trade | F4: No match | G4: No match | H4: United Kingdom | I4: UK tax residence only | J4: UK only | K4: Business account, basic | L4: Withdrawal only | M4: Not enabled | N4: Mandate, evidenced | O4: Branch | P4: Documents face to face | Q4: Direct | R4: Over 25k, consistent | S4: No cash credits | T4: None | U4: Named businesses | V4: Consistent | W4: =INDEX(Mapping!$C$2:$C$99,MATCH("C1|"&C4,Mapping!$D$2:$D$99,0)) -> 3 | X4: =INDEX(Mapping!$C$2:$C$99,MATCH("C2|"&D4,Mapping!$D$2:$D$99,0)) -> 2 | Y4: =INDEX(Mapping!$C$2:$C$99,MATCH("C3|"&E4,Mapping!$D$2:$D$99,0)) -> 4 | Z4: =INDEX(Mapping!$C$2:$C$99,MATCH("C4|"&F4,Mapping!$D$2:$D$99,0)) -> 1 | AA4: =INDEX(Mapping!$C$2:$C$99,MATCH("C5|"&G4,Mapping!$D$2:$D$99,0)) -> 1 | AB4: =INDEX(Mapping!$C$2:$C$99,MATCH("G1|"&H4,Mapping!$D$2:$D$99,0)) -> 1 | AC4: =INDEX(Mapping!$C$2:$C$99,MATCH("G2|"&I4,Mapping!$D$2:$D$99,0)) -> 1 | AD4: =INDEX(Mapping!$C$2:$C$99,MATCH("G3|"&J4,Mapping!$D$2:$D$99,0)) -> 1 | AE4: =INDEX(Mapping!$C$2:$C$99,MATCH("P1|"&K4,Mapping!$D$2:$D$99,0)) -> 4 | AF4: =INDEX(Mapping!$C$2:$C$99,MATCH("P2|"&L4,Mapping!$D$2:$D$99,0)) -> 2 | AG4: =INDEX(Mapping!$C$2:$C$99,MATCH("P3|"&M4,Mapping!$D$2:$D$99,0)) -> 1 | AH4: =INDEX(Mapping!$C$2:$C$99,MATCH("P4|"&N4,Mapping!$D$2:$D$99,0)) -> 3 | AI4: =INDEX(Mapping!$C$2:$C$99,MATCH("D1|"&O4,Mapping!$D$2:$D$99,0)) -> 1 | AJ4: =INDEX(Mapping!$C$2:$C$99,MATCH("D2|"&P4,Mapping!$D$2:$D$99,0)) -> 1 | AK4: =INDEX(Mapping!$C$2:$C$99,MATCH("D3|"&Q4,Mapping!$D$2:$D$99,0)) -> 1 | AL4: =INDEX(Mapping!$C$2:$C$99,MATCH("A1|"&R4,Mapping!$D$2:$D$99,0)) -> 3 | AM4: =INDEX(Mapping!$C$2:$C$99,MATCH("A2|"&S4,Mapping!$D$2:$D$99,0)) -> 1 | AN4: =INDEX(Mapping!$C$2:$C$99,MATCH("A3|"&T4,Mapping!$D$2:$D$99,0)) -> 1 | AO4: =INDEX(Mapping!$C$2:$C$99,MATCH("A4|"&U4,Mapping!$D$2:$D$99,0)) -> 2 | AP4: =INDEX(Mapping!$C$2:$C$99,MATCH("A5|"&V4,Mapping!$D$2:$D$99,0)) -> 1 | AQ4: =SUMPRODUCT($W4:$AP4,Weights!$C$27:$V$27) -> 1.8225 | AR4: =ROUND($AQ4,2) -> 1.82 | AS4: =IF($AR4<=2,"Low",IF($AR4<=3.49,"Medium","High")) -> Low | AT4: =IF(OR($Z4>=3,$Y4=5,$X4=5,$W4=5,$AA4=5,$AB4=5,$AC4=5,$AD4=5),"Yes","No") -> No | AU4: =IF($AT4="Yes","High",$AS4) -> Low | AV4: =SUMPRODUCT($W4:$AA4,Weights!$C$28:$G$28) -> 2.35 | AW4: =SUMPRODUCT($AB4:$AD4,Weights!$H$28:$J$28) -> 1 | AX4: =SUMPRODUCT($AE4:$AH4,Weights!$K$28:$N$28) -> 2.6 | AY4: =SUMPRODUCT($AI4:$AK4,Weights!$O$28:$Q$28) -> 1 | AZ4: =SUMPRODUCT($AL4:$AP4,Weights!$R$28:$V$28) -> 1.65 | BA4: =IF($AR4<=1.6,"Low",IF($AR4<=2.2,"Medium","High")) -> Medium | BB4: =IF(OR($AT4="Yes",$AP4=5),"High",$BA4) -> Medium
A5: FO-mid | B5: NatWest / Fowler Oldfield, same file, high-value dealer reading | C5: UK company, natural owners | D5: One or two UBOs | E5: MSB, TCSP or HVD | F5: No match | G5: No match | H5: United Kingdom | I5: UK tax residence only | J5: UK only | K5: Business account, basic | L5: Withdrawal only | M5: Not enabled | N5: Mandate, evidenced | O5: Branch | P5: Documents face to face | Q5: Direct | R5: Over 25k, consistent | S5: No cash credits | T5: None | U5: Named businesses | V5: Consistent | W5: =INDEX(Mapping!$C$2:$C$99,MATCH("C1|"&C5,Mapping!$D$2:$D$99,0)) -> 3 | X5: =INDEX(Mapping!$C$2:$C$99,MATCH("C2|"&D5,Mapping!$D$2:$D$99,0)) -> 2 | Y5: =INDEX(Mapping!$C$2:$C$99,MATCH("C3|"&E5,Mapping!$D$2:$D$99,0)) -> 5 | Z5: =INDEX(Mapping!$C$2:$C$99,MATCH("C4|"&F5,Mapping!$D$2:$D$99,0)) -> 1 | AA5: =INDEX(Mapping!$C$2:$C$99,MATCH("C5|"&G5,Mapping!$D$2:$D$99,0)) -> 1 | AB5: =INDEX(Mapping!$C$2:$C$99,MATCH("G1|"&H5,Mapping!$D$2:$D$99,0)) -> 1 | AC5: =INDEX(Mapping!$C$2:$C$99,MATCH("G2|"&I5,Mapping!$D$2:$D$99,0)) -> 1 | AD5: =INDEX(Mapping!$C$2:$C$99,MATCH("G3|"&J5,Mapping!$D$2:$D$99,0)) -> 1 | AE5: =INDEX(Mapping!$C$2:$C$99,MATCH("P1|"&K5,Mapping!$D$2:$D$99,0)) -> 4 | AF5: =INDEX(Mapping!$C$2:$C$99,MATCH("P2|"&L5,Mapping!$D$2:$D$99,0)) -> 2 | AG5: =INDEX(Mapping!$C$2:$C$99,MATCH("P3|"&M5,Mapping!$D$2:$D$99,0)) -> 1 | AH5: =INDEX(Mapping!$C$2:$C$99,MATCH("P4|"&N5,Mapping!$D$2:$D$99,0)) -> 3 | AI5: =INDEX(Mapping!$C$2:$C$99,MATCH("D1|"&O5,Mapping!$D$2:$D$99,0)) -> 1 | AJ5: =INDEX(Mapping!$C$2:$C$99,MATCH("D2|"&P5,Mapping!$D$2:$D$99,0)) -> 1 | AK5: =INDEX(Mapping!$C$2:$C$99,MATCH("D3|"&Q5,Mapping!$D$2:$D$99,0)) -> 1 | AL5: =INDEX(Mapping!$C$2:$C$99,MATCH("A1|"&R5,Mapping!$D$2:$D$99,0)) -> 3 | AM5: =INDEX(Mapping!$C$2:$C$99,MATCH("A2|"&S5,Mapping!$D$2:$D$99,0)) -> 1 | AN5: =INDEX(Mapping!$C$2:$C$99,MATCH("A3|"&T5,Mapping!$D$2:$D$99,0)) -> 1 | AO5: =INDEX(Mapping!$C$2:$C$99,MATCH("A4|"&U5,Mapping!$D$2:$D$99,0)) -> 2 | AP5: =INDEX(Mapping!$C$2:$C$99,MATCH("A5|"&V5,Mapping!$D$2:$D$99,0)) -> 1 | AQ5: =SUMPRODUCT($W5:$AP5,Weights!$C$27:$V$27) -> 1.8975 | AR5: =ROUND($AQ5,2) -> 1.9 | AS5: =IF($AR5<=2,"Low",IF($AR5<=3.49,"Medium","High")) -> Low | AT5: =IF(OR($Z5>=3,$Y5=5,$X5=5,$W5=5,$AA5=5,$AB5=5,$AC5=5,$AD5=5),"Yes","No") -> Yes | AU5: =IF($AT5="Yes","High",$AS5) -> High | AV5: =SUMPRODUCT($W5:$AA5,Weights!$C$28:$G$28) -> 2.6 | AW5: =SUMPRODUCT($AB5:$AD5,Weights!$H$28:$J$28) -> 1 | AX5: =SUMPRODUCT($AE5:$AH5,Weights!$K$28:$N$28) -> 2.6 | AY5: =SUMPRODUCT($AI5:$AK5,Weights!$O$28:$Q$28) -> 1 | AZ5: =SUMPRODUCT($AL5:$AP5,Weights!$R$28:$V$28) -> 1.65 | BA5: =IF($AR5<=1.6,"Low",IF($AR5<=2.2,"Medium","High")) -> Medium | BB5: =IF(OR($AT5="Yes",$AP5=5),"High",$BA5) -> High
A6: FO-hi | B6: NatWest / Fowler Oldfield, adverse reading of the open factors | C6: UK company, natural owners | D6: Three to five UBOs | E6: MSB, TCSP or HVD | F6: No match | G6: No match | H6: United Kingdom | I6: UK tax residence only | J6: Unlisted countries | K6: Business account, basic | L6: Under 2k a month | M6: Occasional payments | N6: Mandate, evidenced | O6: Branch | P6: Documents face to face | Q6: Direct | R6: Over 25k, consistent | S6: No cash credits | T6: Up to 10 percent | U6: Many individuals | V6: Consistent | W6: =INDEX(Mapping!$C$2:$C$99,MATCH("C1|"&C6,Mapping!$D$2:$D$99,0)) -> 3 | X6: =INDEX(Mapping!$C$2:$C$99,MATCH("C2|"&D6,Mapping!$D$2:$D$99,0)) -> 3 | Y6: =INDEX(Mapping!$C$2:$C$99,MATCH("C3|"&E6,Mapping!$D$2:$D$99,0)) -> 5 | Z6: =INDEX(Mapping!$C$2:$C$99,MATCH("C4|"&F6,Mapping!$D$2:$D$99,0)) -> 1 | AA6: =INDEX(Mapping!$C$2:$C$99,MATCH("C5|"&G6,Mapping!$D$2:$D$99,0)) -> 1 | AB6: =INDEX(Mapping!$C$2:$C$99,MATCH("G1|"&H6,Mapping!$D$2:$D$99,0)) -> 1 | AC6: =INDEX(Mapping!$C$2:$C$99,MATCH("G2|"&I6,Mapping!$D$2:$D$99,0)) -> 1 | AD6: =INDEX(Mapping!$C$2:$C$99,MATCH("G3|"&J6,Mapping!$D$2:$D$99,0)) -> 2 | AE6: =INDEX(Mapping!$C$2:$C$99,MATCH("P1|"&K6,Mapping!$D$2:$D$99,0)) -> 4 | AF6: =INDEX(Mapping!$C$2:$C$99,MATCH("P2|"&L6,Mapping!$D$2:$D$99,0)) -> 3 | AG6: =INDEX(Mapping!$C$2:$C$99,MATCH("P3|"&M6,Mapping!$D$2:$D$99,0)) -> 3 | AH6: =INDEX(Mapping!$C$2:$C$99,MATCH("P4|"&N6,Mapping!$D$2:$D$99,0)) -> 3 | AI6: =INDEX(Mapping!$C$2:$C$99,MATCH("D1|"&O6,Mapping!$D$2:$D$99,0)) -> 1 | AJ6: =INDEX(Mapping!$C$2:$C$99,MATCH("D2|"&P6,Mapping!$D$2:$D$99,0)) -> 1 | AK6: =INDEX(Mapping!$C$2:$C$99,MATCH("D3|"&Q6,Mapping!$D$2:$D$99,0)) -> 1 | AL6: =INDEX(Mapping!$C$2:$C$99,MATCH("A1|"&R6,Mapping!$D$2:$D$99,0)) -> 3 | AM6: =INDEX(Mapping!$C$2:$C$99,MATCH("A2|"&S6,Mapping!$D$2:$D$99,0)) -> 1 | AN6: =INDEX(Mapping!$C$2:$C$99,MATCH("A3|"&T6,Mapping!$D$2:$D$99,0)) -> 2 | AO6: =INDEX(Mapping!$C$2:$C$99,MATCH("A4|"&U6,Mapping!$D$2:$D$99,0)) -> 3 | AP6: =INDEX(Mapping!$C$2:$C$99,MATCH("A5|"&V6,Mapping!$D$2:$D$99,0)) -> 1 | AQ6: =SUMPRODUCT($W6:$AP6,Weights!$C$27:$V$27) -> 2.26 | AR6: =ROUND($AQ6,2) -> 2.26 | AS6: =IF($AR6<=2,"Low",IF($AR6<=3.49,"Medium","High")) -> Medium | AT6: =IF(OR($Z6>=3,$Y6=5,$X6=5,$W6=5,$AA6=5,$AB6=5,$AC6=5,$AD6=5),"Yes","No") -> Yes | AU6: =IF($AT6="Yes","High",$AS6) -> High | AV6: =SUMPRODUCT($W6:$AA6,Weights!$C$28:$G$28) -> 2.8 | AW6: =SUMPRODUCT($AB6:$AD6,Weights!$H$28:$J$28) -> 1.4 | AX6: =SUMPRODUCT($AE6:$AH6,Weights!$K$28:$N$28) -> 3.35 | AY6: =SUMPRODUCT($AI6:$AK6,Weights!$O$28:$Q$28) -> 1 | AZ6: =SUMPRODUCT($AL6:$AP6,Weights!$R$28:$V$28) -> 2 | BA6: =IF($AR6<=1.6,"Low",IF($AR6<=2.2,"Medium","High")) -> High | BB6: =IF(OR($AT6="Yes",$AP6=5),"High",$BA6) -> High
A7: SAN-a | B7: Santander UK / the translations company, the file as recorded | C7: UK company, natural owners | D7: One or two UBOs | E7: General trade | F7: No match | G7: No match | H7: United Kingdom | I7: UK tax residence only | J7: Unlisted countries | K7: Business account, basic | L7: Under 2k a month | M7: Enabled, unused | N7: Sole party | O7: Branch | P7: Documents face to face | Q7: Direct | R7: 5k to 25k, consistent | S7: Up to 10 percent | T7: Up to 10 percent | U7: Named businesses | V7: Consistent | W7: =INDEX(Mapping!$C$2:$C$99,MATCH("C1|"&C7,Mapping!$D$2:$D$99,0)) -> 3 | X7: =INDEX(Mapping!$C$2:$C$99,MATCH("C2|"&D7,Mapping!$D$2:$D$99,0)) -> 2 | Y7: =INDEX(Mapping!$C$2:$C$99,MATCH("C3|"&E7,Mapping!$D$2:$D$99,0)) -> 3 | Z7: =INDEX(Mapping!$C$2:$C$99,MATCH("C4|"&F7,Mapping!$D$2:$D$99,0)) -> 1 | AA7: =INDEX(Mapping!$C$2:$C$99,MATCH("C5|"&G7,Mapping!$D$2:$D$99,0)) -> 1 | AB7: =INDEX(Mapping!$C$2:$C$99,MATCH("G1|"&H7,Mapping!$D$2:$D$99,0)) -> 1 | AC7: =INDEX(Mapping!$C$2:$C$99,MATCH("G2|"&I7,Mapping!$D$2:$D$99,0)) -> 1 | AD7: =INDEX(Mapping!$C$2:$C$99,MATCH("G3|"&J7,Mapping!$D$2:$D$99,0)) -> 2 | AE7: =INDEX(Mapping!$C$2:$C$99,MATCH("P1|"&K7,Mapping!$D$2:$D$99,0)) -> 4 | AF7: =INDEX(Mapping!$C$2:$C$99,MATCH("P2|"&L7,Mapping!$D$2:$D$99,0)) -> 3 | AG7: =INDEX(Mapping!$C$2:$C$99,MATCH("P3|"&M7,Mapping!$D$2:$D$99,0)) -> 2 | AH7: =INDEX(Mapping!$C$2:$C$99,MATCH("P4|"&N7,Mapping!$D$2:$D$99,0)) -> 1 | AI7: =INDEX(Mapping!$C$2:$C$99,MATCH("D1|"&O7,Mapping!$D$2:$D$99,0)) -> 1 | AJ7: =INDEX(Mapping!$C$2:$C$99,MATCH("D2|"&P7,Mapping!$D$2:$D$99,0)) -> 1 | AK7: =INDEX(Mapping!$C$2:$C$99,MATCH("D3|"&Q7,Mapping!$D$2:$D$99,0)) -> 1 | AL7: =INDEX(Mapping!$C$2:$C$99,MATCH("A1|"&R7,Mapping!$D$2:$D$99,0)) -> 2 | AM7: =INDEX(Mapping!$C$2:$C$99,MATCH("A2|"&S7,Mapping!$D$2:$D$99,0)) -> 2 | AN7: =INDEX(Mapping!$C$2:$C$99,MATCH("A3|"&T7,Mapping!$D$2:$D$99,0)) -> 2 | AO7: =INDEX(Mapping!$C$2:$C$99,MATCH("A4|"&U7,Mapping!$D$2:$D$99,0)) -> 2 | AP7: =INDEX(Mapping!$C$2:$C$99,MATCH("A5|"&V7,Mapping!$D$2:$D$99,0)) -> 1 | AQ7: =SUMPRODUCT($W7:$AP7,Weights!$C$27:$V$27) -> 1.925 | AR7: =ROUND($AQ7,2) -> 1.93 | AS7: =IF($AR7<=2,"Low",IF($AR7<=3.49,"Medium","High")) -> Low | AT7: =IF(OR($Z7>=3,$Y7=5,$X7=5,$W7=5,$AA7=5,$AB7=5,$AC7=5,$AD7=5),"Yes","No") -> No | AU7: =IF($AT7="Yes","High",$AS7) -> Low | AV7: =SUMPRODUCT($W7:$AA7,Weights!$C$28:$G$28) -> 2.1 | AW7: =SUMPRODUCT($AB7:$AD7,Weights!$H$28:$J$28) -> 1.4 | AX7: =SUMPRODUCT($AE7:$AH7,Weights!$K$28:$N$28) -> 2.8 | AY7: =SUMPRODUCT($AI7:$AK7,Weights!$O$28:$Q$28) -> 1 | AZ7: =SUMPRODUCT($AL7:$AP7,Weights!$R$28:$V$28) -> 1.9 | BA7: =IF($AR7<=1.6,"Low",IF($AR7<=2.2,"Medium","High")) -> Medium | BB7: =IF(OR($AT7="Yes",$AP7=5),"High",$BA7) -> Medium
A8: SAN-b | B8: Santander UK / the translations company, with the business verified as an MSB | C8: UK company, natural owners | D8: One or two UBOs | E8: MSB, TCSP or HVD | F8: No match | G8: No match | H8: United Kingdom | I8: UK tax residence only | J8: Unlisted countries | K8: Business account, basic | L8: Under 2k a month | M8: Occasional payments | N8: Sole party | O8: Branch | P8: Documents face to face | Q8: Direct | R8: 5k to 25k, consistent | S8: Up to 10 percent | T8: 10 to 40 percent | U8: Many individuals | V8: Consistent | W8: =INDEX(Mapping!$C$2:$C$99,MATCH("C1|"&C8,Mapping!$D$2:$D$99,0)) -> 3 | X8: =INDEX(Mapping!$C$2:$C$99,MATCH("C2|"&D8,Mapping!$D$2:$D$99,0)) -> 2 | Y8: =INDEX(Mapping!$C$2:$C$99,MATCH("C3|"&E8,Mapping!$D$2:$D$99,0)) -> 5 | Z8: =INDEX(Mapping!$C$2:$C$99,MATCH("C4|"&F8,Mapping!$D$2:$D$99,0)) -> 1 | AA8: =INDEX(Mapping!$C$2:$C$99,MATCH("C5|"&G8,Mapping!$D$2:$D$99,0)) -> 1 | AB8: =INDEX(Mapping!$C$2:$C$99,MATCH("G1|"&H8,Mapping!$D$2:$D$99,0)) -> 1 | AC8: =INDEX(Mapping!$C$2:$C$99,MATCH("G2|"&I8,Mapping!$D$2:$D$99,0)) -> 1 | AD8: =INDEX(Mapping!$C$2:$C$99,MATCH("G3|"&J8,Mapping!$D$2:$D$99,0)) -> 2 | AE8: =INDEX(Mapping!$C$2:$C$99,MATCH("P1|"&K8,Mapping!$D$2:$D$99,0)) -> 4 | AF8: =INDEX(Mapping!$C$2:$C$99,MATCH("P2|"&L8,Mapping!$D$2:$D$99,0)) -> 3 | AG8: =INDEX(Mapping!$C$2:$C$99,MATCH("P3|"&M8,Mapping!$D$2:$D$99,0)) -> 3 | AH8: =INDEX(Mapping!$C$2:$C$99,MATCH("P4|"&N8,Mapping!$D$2:$D$99,0)) -> 1 | AI8: =INDEX(Mapping!$C$2:$C$99,MATCH("D1|"&O8,Mapping!$D$2:$D$99,0)) -> 1 | AJ8: =INDEX(Mapping!$C$2:$C$99,MATCH("D2|"&P8,Mapping!$D$2:$D$99,0)) -> 1 | AK8: =INDEX(Mapping!$C$2:$C$99,MATCH("D3|"&Q8,Mapping!$D$2:$D$99,0)) -> 1 | AL8: =INDEX(Mapping!$C$2:$C$99,MATCH("A1|"&R8,Mapping!$D$2:$D$99,0)) -> 2 | AM8: =INDEX(Mapping!$C$2:$C$99,MATCH("A2|"&S8,Mapping!$D$2:$D$99,0)) -> 2 | AN8: =INDEX(Mapping!$C$2:$C$99,MATCH("A3|"&T8,Mapping!$D$2:$D$99,0)) -> 3 | AO8: =INDEX(Mapping!$C$2:$C$99,MATCH("A4|"&U8,Mapping!$D$2:$D$99,0)) -> 3 | AP8: =INDEX(Mapping!$C$2:$C$99,MATCH("A5|"&V8,Mapping!$D$2:$D$99,0)) -> 1 | AQ8: =SUMPRODUCT($W8:$AP8,Weights!$C$27:$V$27) -> 2.1775 | AR8: =ROUND($AQ8,2) -> 2.18 | AS8: =IF($AR8<=2,"Low",IF($AR8<=3.49,"Medium","High")) -> Medium | AT8: =IF(OR($Z8>=3,$Y8=5,$X8=5,$W8=5,$AA8=5,$AB8=5,$AC8=5,$AD8=5),"Yes","No") -> Yes | AU8: =IF($AT8="Yes","High",$AS8) -> High | AV8: =SUMPRODUCT($W8:$AA8,Weights!$C$28:$G$28) -> 2.6 | AW8: =SUMPRODUCT($AB8:$AD8,Weights!$H$28:$J$28) -> 1.4 | AX8: =SUMPRODUCT($AE8:$AH8,Weights!$K$28:$N$28) -> 3.05 | AY8: =SUMPRODUCT($AI8:$AK8,Weights!$O$28:$Q$28) -> 1 | AZ8: =SUMPRODUCT($AL8:$AP8,Weights!$R$28:$V$28) -> 2.25 | BA8: =IF($AR8<=1.6,"Low",IF($AR8<=2.2,"Medium","High")) -> Medium | BB8: =IF(OR($AT8="Yes",$AP8=5),"High",$BA8) -> High
A9: STU-a | B9: Barclays / Stunt & Co, the application file of 16 January 2015 | C9: UK company, natural owners | D9: One or two UBOs | E9: MSB, TCSP or HVD | F9: No match | G9: No match | H9: United Kingdom | I9: UK tax residence only | J9: Unlisted countries | K9: Business account, basic | L9: Withdrawal only | M9: Occasional payments | N9: Sole party | O9: Branch | P9: Documents face to face | Q9: Direct | R9: Over 25k, consistent | S9: No cash credits | T9: 10 to 40 percent | U9: Named businesses | V9: Unresolved | W9: =INDEX(Mapping!$C$2:$C$99,MATCH("C1|"&C9,Mapping!$D$2:$D$99,0)) -> 3 | X9: =INDEX(Mapping!$C$2:$C$99,MATCH("C2|"&D9,Mapping!$D$2:$D$99,0)) -> 2 | Y9: =INDEX(Mapping!$C$2:$C$99,MATCH("C3|"&E9,Mapping!$D$2:$D$99,0)) -> 5 | Z9: =INDEX(Mapping!$C$2:$C$99,MATCH("C4|"&F9,Mapping!$D$2:$D$99,0)) -> 1 | AA9: =INDEX(Mapping!$C$2:$C$99,MATCH("C5|"&G9,Mapping!$D$2:$D$99,0)) -> 1 | AB9: =INDEX(Mapping!$C$2:$C$99,MATCH("G1|"&H9,Mapping!$D$2:$D$99,0)) -> 1 | AC9: =INDEX(Mapping!$C$2:$C$99,MATCH("G2|"&I9,Mapping!$D$2:$D$99,0)) -> 1 | AD9: =INDEX(Mapping!$C$2:$C$99,MATCH("G3|"&J9,Mapping!$D$2:$D$99,0)) -> 2 | AE9: =INDEX(Mapping!$C$2:$C$99,MATCH("P1|"&K9,Mapping!$D$2:$D$99,0)) -> 4 | AF9: =INDEX(Mapping!$C$2:$C$99,MATCH("P2|"&L9,Mapping!$D$2:$D$99,0)) -> 2 | AG9: =INDEX(Mapping!$C$2:$C$99,MATCH("P3|"&M9,Mapping!$D$2:$D$99,0)) -> 3 | AH9: =INDEX(Mapping!$C$2:$C$99,MATCH("P4|"&N9,Mapping!$D$2:$D$99,0)) -> 1 | AI9: =INDEX(Mapping!$C$2:$C$99,MATCH("D1|"&O9,Mapping!$D$2:$D$99,0)) -> 1 | AJ9: =INDEX(Mapping!$C$2:$C$99,MATCH("D2|"&P9,Mapping!$D$2:$D$99,0)) -> 1 | AK9: =INDEX(Mapping!$C$2:$C$99,MATCH("D3|"&Q9,Mapping!$D$2:$D$99,0)) -> 1 | AL9: =INDEX(Mapping!$C$2:$C$99,MATCH("A1|"&R9,Mapping!$D$2:$D$99,0)) -> 3 | AM9: =INDEX(Mapping!$C$2:$C$99,MATCH("A2|"&S9,Mapping!$D$2:$D$99,0)) -> 1 | AN9: =INDEX(Mapping!$C$2:$C$99,MATCH("A3|"&T9,Mapping!$D$2:$D$99,0)) -> 3 | AO9: =INDEX(Mapping!$C$2:$C$99,MATCH("A4|"&U9,Mapping!$D$2:$D$99,0)) -> 2 | AP9: =INDEX(Mapping!$C$2:$C$99,MATCH("A5|"&V9,Mapping!$D$2:$D$99,0)) -> 4 | AQ9: =SUMPRODUCT($W9:$AP9,Weights!$C$27:$V$27) -> 2.1425 | AR9: =ROUND($AQ9,2) -> 2.14 | AS9: =IF($AR9<=2,"Low",IF($AR9<=3.49,"Medium","High")) -> Medium | AT9: =IF(OR($Z9>=3,$Y9=5,$X9=5,$W9=5,$AA9=5,$AB9=5,$AC9=5,$AD9=5),"Yes","No") -> Yes | AU9: =IF($AT9="Yes","High",$AS9) -> High | AV9: =SUMPRODUCT($W9:$AA9,Weights!$C$28:$G$28) -> 2.6 | AW9: =SUMPRODUCT($AB9:$AD9,Weights!$H$28:$J$28) -> 1.4 | AX9: =SUMPRODUCT($AE9:$AH9,Weights!$K$28:$N$28) -> 2.8 | AY9: =SUMPRODUCT($AI9:$AK9,Weights!$O$28:$Q$28) -> 1 | AZ9: =SUMPRODUCT($AL9:$AP9,Weights!$R$28:$V$28) -> 2.35 | BA9: =IF($AR9<=1.6,"Low",IF($AR9<=2.2,"Medium","High")) -> Medium | BB9: =IF(OR($AT9="Yes",$AP9=5),"High",$BA9) -> High
A10: STU-b | B10: Barclays / Stunt & Co, the same file after the meeting of 27 January 2015 | C10: UK company, natural owners | D10: One or two UBOs | E10: MSB, TCSP or HVD | F10: No match | G10: No match | H10: United Kingdom | I10: UK tax residence only | J10: Weaker AML, unlisted | K10: Business account, basic | L10: Withdrawal only | M10: Occasional payments | N10: Sole party | O10: Branch | P10: Documents face to face | Q10: Direct | R10: Over 25k, consistent | S10: No cash credits | T10: Over 40 percent | U10: Named businesses | V10: Not credible | W10: =INDEX(Mapping!$C$2:$C$99,MATCH("C1|"&C10,Mapping!$D$2:$D$99,0)) -> 3 | X10: =INDEX(Mapping!$C$2:$C$99,MATCH("C2|"&D10,Mapping!$D$2:$D$99,0)) -> 2 | Y10: =INDEX(Mapping!$C$2:$C$99,MATCH("C3|"&E10,Mapping!$D$2:$D$99,0)) -> 5 | Z10: =INDEX(Mapping!$C$2:$C$99,MATCH("C4|"&F10,Mapping!$D$2:$D$99,0)) -> 1 | AA10: =INDEX(Mapping!$C$2:$C$99,MATCH("C5|"&G10,Mapping!$D$2:$D$99,0)) -> 1 | AB10: =INDEX(Mapping!$C$2:$C$99,MATCH("G1|"&H10,Mapping!$D$2:$D$99,0)) -> 1 | AC10: =INDEX(Mapping!$C$2:$C$99,MATCH("G2|"&I10,Mapping!$D$2:$D$99,0)) -> 1 | AD10: =INDEX(Mapping!$C$2:$C$99,MATCH("G3|"&J10,Mapping!$D$2:$D$99,0)) -> 3 | AE10: =INDEX(Mapping!$C$2:$C$99,MATCH("P1|"&K10,Mapping!$D$2:$D$99,0)) -> 4 | AF10: =INDEX(Mapping!$C$2:$C$99,MATCH("P2|"&L10,Mapping!$D$2:$D$99,0)) -> 2 | AG10: =INDEX(Mapping!$C$2:$C$99,MATCH("P3|"&M10,Mapping!$D$2:$D$99,0)) -> 3 | AH10: =INDEX(Mapping!$C$2:$C$99,MATCH("P4|"&N10,Mapping!$D$2:$D$99,0)) -> 1 | AI10: =INDEX(Mapping!$C$2:$C$99,MATCH("D1|"&O10,Mapping!$D$2:$D$99,0)) -> 1 | AJ10: =INDEX(Mapping!$C$2:$C$99,MATCH("D2|"&P10,Mapping!$D$2:$D$99,0)) -> 1 | AK10: =INDEX(Mapping!$C$2:$C$99,MATCH("D3|"&Q10,Mapping!$D$2:$D$99,0)) -> 1 | AL10: =INDEX(Mapping!$C$2:$C$99,MATCH("A1|"&R10,Mapping!$D$2:$D$99,0)) -> 3 | AM10: =INDEX(Mapping!$C$2:$C$99,MATCH("A2|"&S10,Mapping!$D$2:$D$99,0)) -> 1 | AN10: =INDEX(Mapping!$C$2:$C$99,MATCH("A3|"&T10,Mapping!$D$2:$D$99,0)) -> 4 | AO10: =INDEX(Mapping!$C$2:$C$99,MATCH("A4|"&U10,Mapping!$D$2:$D$99,0)) -> 2 | AP10: =INDEX(Mapping!$C$2:$C$99,MATCH("A5|"&V10,Mapping!$D$2:$D$99,0)) -> 5 | AQ10: =SUMPRODUCT($W10:$AP10,Weights!$C$27:$V$27) -> 2.2875 | AR10: =ROUND($AQ10,2) -> 2.29 | AS10: =IF($AR10<=2,"Low",IF($AR10<=3.49,"Medium","High")) -> Medium | AT10: =IF(OR($Z10>=3,$Y10=5,$X10=5,$W10=5,$AA10=5,$AB10=5,$AC10=5,$AD10=5),"Yes","No") -> Yes | AU10: =IF($AT10="Yes","High",$AS10) -> High | AV10: =SUMPRODUCT($W10:$AA10,Weights!$C$28:$G$28) -> 2.6 | AW10: =SUMPRODUCT($AB10:$AD10,Weights!$H$28:$J$28) -> 1.8 | AX10: =SUMPRODUCT($AE10:$AH10,Weights!$K$28:$N$28) -> 2.8 | AY10: =SUMPRODUCT($AI10:$AK10,Weights!$O$28:$Q$28) -> 1 | AZ10: =SUMPRODUCT($AL10:$AP10,Weights!$R$28:$V$28) -> 2.65 | BA10: =IF($AR10<=1.6,"Low",IF($AR10<=2.2,"Medium","High")) -> High | BB10: =IF(OR($AT10="Yes",$AP10=5),"High",$BA10) -> High
A11: WTK-lo | B11: Barclays / WealthTek, favourable reading | C11: UK company, natural owners | D11: One or two UBOs | E11: Regulated profession | F11: No match | G11: No match | H11: United Kingdom | I11: UK tax residence only | J11: UK only | K11: Business account, basic | L11: No cash facility | M11: Regular payments | N11: Mandate, evidenced | O11: Branch | P11: Documents face to face | Q11: Direct | R11: Over 25k, consistent | S11: No cash credits | T11: Up to 10 percent | U11: Many individuals | V11: Consistent | W11: =INDEX(Mapping!$C$2:$C$99,MATCH("C1|"&C11,Mapping!$D$2:$D$99,0)) -> 3 | X11: =INDEX(Mapping!$C$2:$C$99,MATCH("C2|"&D11,Mapping!$D$2:$D$99,0)) -> 2 | Y11: =INDEX(Mapping!$C$2:$C$99,MATCH("C3|"&E11,Mapping!$D$2:$D$99,0)) -> 2 | Z11: =INDEX(Mapping!$C$2:$C$99,MATCH("C4|"&F11,Mapping!$D$2:$D$99,0)) -> 1 | AA11: =INDEX(Mapping!$C$2:$C$99,MATCH("C5|"&G11,Mapping!$D$2:$D$99,0)) -> 1 | AB11: =INDEX(Mapping!$C$2:$C$99,MATCH("G1|"&H11,Mapping!$D$2:$D$99,0)) -> 1 | AC11: =INDEX(Mapping!$C$2:$C$99,MATCH("G2|"&I11,Mapping!$D$2:$D$99,0)) -> 1 | AD11: =INDEX(Mapping!$C$2:$C$99,MATCH("G3|"&J11,Mapping!$D$2:$D$99,0)) -> 1 | AE11: =INDEX(Mapping!$C$2:$C$99,MATCH("P1|"&K11,Mapping!$D$2:$D$99,0)) -> 4 | AF11: =INDEX(Mapping!$C$2:$C$99,MATCH("P2|"&L11,Mapping!$D$2:$D$99,0)) -> 1 | AG11: =INDEX(Mapping!$C$2:$C$99,MATCH("P3|"&M11,Mapping!$D$2:$D$99,0)) -> 4 | AH11: =INDEX(Mapping!$C$2:$C$99,MATCH("P4|"&N11,Mapping!$D$2:$D$99,0)) -> 3 | AI11: =INDEX(Mapping!$C$2:$C$99,MATCH("D1|"&O11,Mapping!$D$2:$D$99,0)) -> 1 | AJ11: =INDEX(Mapping!$C$2:$C$99,MATCH("D2|"&P11,Mapping!$D$2:$D$99,0)) -> 1 | AK11: =INDEX(Mapping!$C$2:$C$99,MATCH("D3|"&Q11,Mapping!$D$2:$D$99,0)) -> 1 | AL11: =INDEX(Mapping!$C$2:$C$99,MATCH("A1|"&R11,Mapping!$D$2:$D$99,0)) -> 3 | AM11: =INDEX(Mapping!$C$2:$C$99,MATCH("A2|"&S11,Mapping!$D$2:$D$99,0)) -> 1 | AN11: =INDEX(Mapping!$C$2:$C$99,MATCH("A3|"&T11,Mapping!$D$2:$D$99,0)) -> 2 | AO11: =INDEX(Mapping!$C$2:$C$99,MATCH("A4|"&U11,Mapping!$D$2:$D$99,0)) -> 3 | AP11: =INDEX(Mapping!$C$2:$C$99,MATCH("A5|"&V11,Mapping!$D$2:$D$99,0)) -> 1 | AQ11: =SUMPRODUCT($W11:$AP11,Weights!$C$27:$V$27) -> 1.825 | AR11: =ROUND($AQ11,2) -> 1.83 | AS11: =IF($AR11<=2,"Low",IF($AR11<=3.49,"Medium","High")) -> Low | AT11: =IF(OR($Z11>=3,$Y11=5,$X11=5,$W11=5,$AA11=5,$AB11=5,$AC11=5,$AD11=5),"Yes","No") -> No | AU11: =IF($AT11="Yes","High",$AS11) -> Low | AV11: =SUMPRODUCT($W11:$AA11,Weights!$C$28:$G$28) -> 1.85 | AW11: =SUMPRODUCT($AB11:$AD11,Weights!$H$28:$J$28) -> 1 | AX11: =SUMPRODUCT($AE11:$AH11,Weights!$K$28:$N$28) -> 3.1 | AY11: =SUMPRODUCT($AI11:$AK11,Weights!$O$28:$Q$28) -> 1 | AZ11: =SUMPRODUCT($AL11:$AP11,Weights!$R$28:$V$28) -> 2 | BA11: =IF($AR11<=1.6,"Low",IF($AR11<=2.2,"Medium","High")) -> Medium | BB11: =IF(OR($AT11="Yes",$AP11=5),"High",$BA11) -> Medium
A12: WTK-hi | B12: Barclays / WealthTek, adverse reading | C12: UK company, natural owners | D12: Three to five UBOs | E12: Regulated profession | F12: No match | G12: No match | H12: United Kingdom | I12: UK tax residence only | J12: Unlisted countries | K12: Business account, basic | L12: No cash facility | M12: Regular payments | N12: Mandate, evidenced | O12: Branch | P12: Certified copies | Q12: Direct | R12: Over 25k, consistent | S12: No cash credits | T12: 10 to 40 percent | U12: Many individuals | V12: Consistent | W12: =INDEX(Mapping!$C$2:$C$99,MATCH("C1|"&C12,Mapping!$D$2:$D$99,0)) -> 3 | X12: =INDEX(Mapping!$C$2:$C$99,MATCH("C2|"&D12,Mapping!$D$2:$D$99,0)) -> 3 | Y12: =INDEX(Mapping!$C$2:$C$99,MATCH("C3|"&E12,Mapping!$D$2:$D$99,0)) -> 2 | Z12: =INDEX(Mapping!$C$2:$C$99,MATCH("C4|"&F12,Mapping!$D$2:$D$99,0)) -> 1 | AA12: =INDEX(Mapping!$C$2:$C$99,MATCH("C5|"&G12,Mapping!$D$2:$D$99,0)) -> 1 | AB12: =INDEX(Mapping!$C$2:$C$99,MATCH("G1|"&H12,Mapping!$D$2:$D$99,0)) -> 1 | AC12: =INDEX(Mapping!$C$2:$C$99,MATCH("G2|"&I12,Mapping!$D$2:$D$99,0)) -> 1 | AD12: =INDEX(Mapping!$C$2:$C$99,MATCH("G3|"&J12,Mapping!$D$2:$D$99,0)) -> 2 | AE12: =INDEX(Mapping!$C$2:$C$99,MATCH("P1|"&K12,Mapping!$D$2:$D$99,0)) -> 4 | AF12: =INDEX(Mapping!$C$2:$C$99,MATCH("P2|"&L12,Mapping!$D$2:$D$99,0)) -> 1 | AG12: =INDEX(Mapping!$C$2:$C$99,MATCH("P3|"&M12,Mapping!$D$2:$D$99,0)) -> 4 | AH12: =INDEX(Mapping!$C$2:$C$99,MATCH("P4|"&N12,Mapping!$D$2:$D$99,0)) -> 3 | AI12: =INDEX(Mapping!$C$2:$C$99,MATCH("D1|"&O12,Mapping!$D$2:$D$99,0)) -> 1 | AJ12: =INDEX(Mapping!$C$2:$C$99,MATCH("D2|"&P12,Mapping!$D$2:$D$99,0)) -> 2 | AK12: =INDEX(Mapping!$C$2:$C$99,MATCH("D3|"&Q12,Mapping!$D$2:$D$99,0)) -> 1 | AL12: =INDEX(Mapping!$C$2:$C$99,MATCH("A1|"&R12,Mapping!$D$2:$D$99,0)) -> 3 | AM12: =INDEX(Mapping!$C$2:$C$99,MATCH("A2|"&S12,Mapping!$D$2:$D$99,0)) -> 1 | AN12: =INDEX(Mapping!$C$2:$C$99,MATCH("A3|"&T12,Mapping!$D$2:$D$99,0)) -> 3 | AO12: =INDEX(Mapping!$C$2:$C$99,MATCH("A4|"&U12,Mapping!$D$2:$D$99,0)) -> 3 | AP12: =INDEX(Mapping!$C$2:$C$99,MATCH("A5|"&V12,Mapping!$D$2:$D$99,0)) -> 1 | AQ12: =SUMPRODUCT($W12:$AP12,Weights!$C$27:$V$27) -> 2.05 | AR12: =ROUND($AQ12,2) -> 2.05 | AS12: =IF($AR12<=2,"Low",IF($AR12<=3.49,"Medium","High")) -> Medium | AT12: =IF(OR($Z12>=3,$Y12=5,$X12=5,$W12=5,$AA12=5,$AB12=5,$AC12=5,$AD12=5),"Yes","No") -> No | AU12: =IF($AT12="Yes","High",$AS12) -> Medium | AV12: =SUMPRODUCT($W12:$AA12,Weights!$C$28:$G$28) -> 2.05 | AW12: =SUMPRODUCT($AB12:$AD12,Weights!$H$28:$J$28) -> 1.4 | AX12: =SUMPRODUCT($AE12:$AH12,Weights!$K$28:$N$28) -> 3.1 | AY12: =SUMPRODUCT($AI12:$AK12,Weights!$O$28:$Q$28) -> 1.35 | AZ12: =SUMPRODUCT($AL12:$AP12,Weights!$R$28:$V$28) -> 2.2 | BA12: =IF($AR12<=1.6,"Low",IF($AR12<=2.2,"Medium","High")) -> Medium | BB12: =IF(OR($AT12="Yes",$AP12=5),"High",$BA12) -> Medium
A13: MON-lo | B13: Monzo / the landmark address, favourable reading | C13: Individual | D13: Natural person | E13: Employed or pension | F13: No match | G13: No match | H13: United Kingdom | I13: UK tax residence only | J13: UK only | K13: Current account, no overdraft | L13: Under 2k a month | M13: Enabled, unused | N13: Sole party | O13: Digital, own app | P13: Electronic, one source | Q13: Direct | R13: Under 5k, consistent | S13: Up to 10 percent | T13: None | U13: Employer and retail | V13: Not credible | W13: =INDEX(Mapping!$C$2:$C$99,MATCH("C1|"&C13,Mapping!$D$2:$D$99,0)) -> 1 | X13: =INDEX(Mapping!$C$2:$C$99,MATCH("C2|"&D13,Mapping!$D$2:$D$99,0)) -> 1 | Y13: =INDEX(Mapping!$C$2:$C$99,MATCH("C3|"&E13,Mapping!$D$2:$D$99,0)) -> 1 | Z13: =INDEX(Mapping!$C$2:$C$99,MATCH("C4|"&F13,Mapping!$D$2:$D$99,0)) -> 1 | AA13: =INDEX(Mapping!$C$2:$C$99,MATCH("C5|"&G13,Mapping!$D$2:$D$99,0)) -> 1 | AB13: =INDEX(Mapping!$C$2:$C$99,MATCH("G1|"&H13,Mapping!$D$2:$D$99,0)) -> 1 | AC13: =INDEX(Mapping!$C$2:$C$99,MATCH("G2|"&I13,Mapping!$D$2:$D$99,0)) -> 1 | AD13: =INDEX(Mapping!$C$2:$C$99,MATCH("G3|"&J13,Mapping!$D$2:$D$99,0)) -> 1 | AE13: =INDEX(Mapping!$C$2:$C$99,MATCH("P1|"&K13,Mapping!$D$2:$D$99,0)) -> 2 | AF13: =INDEX(Mapping!$C$2:$C$99,MATCH("P2|"&L13,Mapping!$D$2:$D$99,0)) -> 3 | AG13: =INDEX(Mapping!$C$2:$C$99,MATCH("P3|"&M13,Mapping!$D$2:$D$99,0)) -> 2 | AH13: =INDEX(Mapping!$C$2:$C$99,MATCH("P4|"&N13,Mapping!$D$2:$D$99,0)) -> 1 | AI13: =INDEX(Mapping!$C$2:$C$99,MATCH("D1|"&O13,Mapping!$D$2:$D$99,0)) -> 3 | AJ13: =INDEX(Mapping!$C$2:$C$99,MATCH("D2|"&P13,Mapping!$D$2:$D$99,0)) -> 4 | AK13: =INDEX(Mapping!$C$2:$C$99,MATCH("D3|"&Q13,Mapping!$D$2:$D$99,0)) -> 1 | AL13: =INDEX(Mapping!$C$2:$C$99,MATCH("A1|"&R13,Mapping!$D$2:$D$99,0)) -> 1 | AM13: =INDEX(Mapping!$C$2:$C$99,MATCH("A2|"&S13,Mapping!$D$2:$D$99,0)) -> 2 | AN13: =INDEX(Mapping!$C$2:$C$99,MATCH("A3|"&T13,Mapping!$D$2:$D$99,0)) -> 1 | AO13: =INDEX(Mapping!$C$2:$C$99,MATCH("A4|"&U13,Mapping!$D$2:$D$99,0)) -> 1 | AP13: =INDEX(Mapping!$C$2:$C$99,MATCH("A5|"&V13,Mapping!$D$2:$D$99,0)) -> 5 | AQ13: =SUMPRODUCT($W13:$AP13,Weights!$C$27:$V$27) -> 1.52 | AR13: =ROUND($AQ13,2) -> 1.52 | AS13: =IF($AR13<=2,"Low",IF($AR13<=3.49,"Medium","High")) -> Low | AT13: =IF(OR($Z13>=3,$Y13=5,$X13=5,$W13=5,$AA13=5,$AB13=5,$AC13=5,$AD13=5),"Yes","No") -> No | AU13: =IF($AT13="Yes","High",$AS13) -> Low | AV13: =SUMPRODUCT($W13:$AA13,Weights!$C$28:$G$28) -> 1 | AW13: =SUMPRODUCT($AB13:$AD13,Weights!$H$28:$J$28) -> 1 | AX13: =SUMPRODUCT($AE13:$AH13,Weights!$K$28:$N$28) -> 2.1 | AY13: =SUMPRODUCT($AI13:$AK13,Weights!$O$28:$Q$28) -> 2.95 | AZ13: =SUMPRODUCT($AL13:$AP13,Weights!$R$28:$V$28) -> 1.7 | BA13: =IF($AR13<=1.6,"Low",IF($AR13<=2.2,"Medium","High")) -> Low | BB13: =IF(OR($AT13="Yes",$AP13=5),"High",$BA13) -> High
A14: MON-hi | B14: Monzo / the landmark address, adverse reading | C14: Individual | D14: Natural person | E14: Employed or pension | F14: No match | G14: No match | H14: United Kingdom | I14: UK tax residence only | J14: UK only | K14: Current account with credit | L14: Under 2k a month | M14: Enabled, unused | N14: Sole party | O14: Digital, own app | P14: Uncorroborated documents | Q14: Direct | R14: Under 5k, consistent | S14: 10 to 30 percent | T14: None | U14: Employer and retail | V14: Not credible | W14: =INDEX(Mapping!$C$2:$C$99,MATCH("C1|"&C14,Mapping!$D$2:$D$99,0)) -> 1 | X14: =INDEX(Mapping!$C$2:$C$99,MATCH("C2|"&D14,Mapping!$D$2:$D$99,0)) -> 1 | Y14: =INDEX(Mapping!$C$2:$C$99,MATCH("C3|"&E14,Mapping!$D$2:$D$99,0)) -> 1 | Z14: =INDEX(Mapping!$C$2:$C$99,MATCH("C4|"&F14,Mapping!$D$2:$D$99,0)) -> 1 | AA14: =INDEX(Mapping!$C$2:$C$99,MATCH("C5|"&G14,Mapping!$D$2:$D$99,0)) -> 1 | AB14: =INDEX(Mapping!$C$2:$C$99,MATCH("G1|"&H14,Mapping!$D$2:$D$99,0)) -> 1 | AC14: =INDEX(Mapping!$C$2:$C$99,MATCH("G2|"&I14,Mapping!$D$2:$D$99,0)) -> 1 | AD14: =INDEX(Mapping!$C$2:$C$99,MATCH("G3|"&J14,Mapping!$D$2:$D$99,0)) -> 1 | AE14: =INDEX(Mapping!$C$2:$C$99,MATCH("P1|"&K14,Mapping!$D$2:$D$99,0)) -> 3 | AF14: =INDEX(Mapping!$C$2:$C$99,MATCH("P2|"&L14,Mapping!$D$2:$D$99,0)) -> 3 | AG14: =INDEX(Mapping!$C$2:$C$99,MATCH("P3|"&M14,Mapping!$D$2:$D$99,0)) -> 2 | AH14: =INDEX(Mapping!$C$2:$C$99,MATCH("P4|"&N14,Mapping!$D$2:$D$99,0)) -> 1 | AI14: =INDEX(Mapping!$C$2:$C$99,MATCH("D1|"&O14,Mapping!$D$2:$D$99,0)) -> 3 | AJ14: =INDEX(Mapping!$C$2:$C$99,MATCH("D2|"&P14,Mapping!$D$2:$D$99,0)) -> 5 | AK14: =INDEX(Mapping!$C$2:$C$99,MATCH("D3|"&Q14,Mapping!$D$2:$D$99,0)) -> 1 | AL14: =INDEX(Mapping!$C$2:$C$99,MATCH("A1|"&R14,Mapping!$D$2:$D$99,0)) -> 1 | AM14: =INDEX(Mapping!$C$2:$C$99,MATCH("A2|"&S14,Mapping!$D$2:$D$99,0)) -> 3 | AN14: =INDEX(Mapping!$C$2:$C$99,MATCH("A3|"&T14,Mapping!$D$2:$D$99,0)) -> 1 | AO14: =INDEX(Mapping!$C$2:$C$99,MATCH("A4|"&U14,Mapping!$D$2:$D$99,0)) -> 1 | AP14: =INDEX(Mapping!$C$2:$C$99,MATCH("A5|"&V14,Mapping!$D$2:$D$99,0)) -> 5 | AQ14: =SUMPRODUCT($W14:$AP14,Weights!$C$27:$V$27) -> 1.67 | AR14: =ROUND($AQ14,2) -> 1.67 | AS14: =IF($AR14<=2,"Low",IF($AR14<=3.49,"Medium","High")) -> Low | AT14: =IF(OR($Z14>=3,$Y14=5,$X14=5,$W14=5,$AA14=5,$AB14=5,$AC14=5,$AD14=5),"Yes","No") -> No | AU14: =IF($AT14="Yes","High",$AS14) -> Low | AV14: =SUMPRODUCT($W14:$AA14,Weights!$C$28:$G$28) -> 1 | AW14: =SUMPRODUCT($AB14:$AD14,Weights!$H$28:$J$28) -> 1 | AX14: =SUMPRODUCT($AE14:$AH14,Weights!$K$28:$N$28) -> 2.45 | AY14: =SUMPRODUCT($AI14:$AK14,Weights!$O$28:$Q$28) -> 3.3 | AZ14: =SUMPRODUCT($AL14:$AP14,Weights!$R$28:$V$28) -> 2 | BA14: =IF($AR14<=1.6,"Low",IF($AR14<=2.2,"Medium","High")) -> Medium | BB14: =IF(OR($AT14="Yes",$AP14=5),"High",$BA14) -> High
A15: NAT-lo | B15: Nationwide / the personal account used for business, favourable reading | C15: Individual | D15: Natural person | E15: Employed or pension | F15: No match | G15: No match | H15: United Kingdom | I15: UK tax residence only | J15: UK only | K15: Current account with credit | L15: Under 2k a month | M15: Enabled, unused | N15: Sole party | O15: Digital, own app | P15: Electronic, two sources | Q15: Direct | R15: Under 5k, consistent | S15: Up to 10 percent | T15: None | U15: Employer and retail | V15: Consistent | W15: =INDEX(Mapping!$C$2:$C$99,MATCH("C1|"&C15,Mapping!$D$2:$D$99,0)) -> 1 | X15: =INDEX(Mapping!$C$2:$C$99,MATCH("C2|"&D15,Mapping!$D$2:$D$99,0)) -> 1 | Y15: =INDEX(Mapping!$C$2:$C$99,MATCH("C3|"&E15,Mapping!$D$2:$D$99,0)) -> 1 | Z15: =INDEX(Mapping!$C$2:$C$99,MATCH("C4|"&F15,Mapping!$D$2:$D$99,0)) -> 1 | AA15: =INDEX(Mapping!$C$2:$C$99,MATCH("C5|"&G15,Mapping!$D$2:$D$99,0)) -> 1 | AB15: =INDEX(Mapping!$C$2:$C$99,MATCH("G1|"&H15,Mapping!$D$2:$D$99,0)) -> 1 | AC15: =INDEX(Mapping!$C$2:$C$99,MATCH("G2|"&I15,Mapping!$D$2:$D$99,0)) -> 1 | AD15: =INDEX(Mapping!$C$2:$C$99,MATCH("G3|"&J15,Mapping!$D$2:$D$99,0)) -> 1 | AE15: =INDEX(Mapping!$C$2:$C$99,MATCH("P1|"&K15,Mapping!$D$2:$D$99,0)) -> 3 | AF15: =INDEX(Mapping!$C$2:$C$99,MATCH("P2|"&L15,Mapping!$D$2:$D$99,0)) -> 3 | AG15: =INDEX(Mapping!$C$2:$C$99,MATCH("P3|"&M15,Mapping!$D$2:$D$99,0)) -> 2 | AH15: =INDEX(Mapping!$C$2:$C$99,MATCH("P4|"&N15,Mapping!$D$2:$D$99,0)) -> 1 | AI15: =INDEX(Mapping!$C$2:$C$99,MATCH("D1|"&O15,Mapping!$D$2:$D$99,0)) -> 3 | AJ15: =INDEX(Mapping!$C$2:$C$99,MATCH("D2|"&P15,Mapping!$D$2:$D$99,0)) -> 3 | AK15: =INDEX(Mapping!$C$2:$C$99,MATCH("D3|"&Q15,Mapping!$D$2:$D$99,0)) -> 1 | AL15: =INDEX(Mapping!$C$2:$C$99,MATCH("A1|"&R15,Mapping!$D$2:$D$99,0)) -> 1 | AM15: =INDEX(Mapping!$C$2:$C$99,MATCH("A2|"&S15,Mapping!$D$2:$D$99,0)) -> 2 | AN15: =INDEX(Mapping!$C$2:$C$99,MATCH("A3|"&T15,Mapping!$D$2:$D$99,0)) -> 1 | AO15: =INDEX(Mapping!$C$2:$C$99,MATCH("A4|"&U15,Mapping!$D$2:$D$99,0)) -> 1 | AP15: =INDEX(Mapping!$C$2:$C$99,MATCH("A5|"&V15,Mapping!$D$2:$D$99,0)) -> 1 | AQ15: =SUMPRODUCT($W15:$AP15,Weights!$C$27:$V$27) -> 1.495 | AR15: =ROUND($AQ15,2) -> 1.5 | AS15: =IF($AR15<=2,"Low",IF($AR15<=3.49,"Medium","High")) -> Low | AT15: =IF(OR($Z15>=3,$Y15=5,$X15=5,$W15=5,$AA15=5,$AB15=5,$AC15=5,$AD15=5),"Yes","No") -> No | AU15: =IF($AT15="Yes","High",$AS15) -> Low | AV15: =SUMPRODUCT($W15:$AA15,Weights!$C$28:$G$28) -> 1 | AW15: =SUMPRODUCT($AB15:$AD15,Weights!$H$28:$J$28) -> 1 | AX15: =SUMPRODUCT($AE15:$AH15,Weights!$K$28:$N$28) -> 2.45 | AY15: =SUMPRODUCT($AI15:$AK15,Weights!$O$28:$Q$28) -> 2.6 | AZ15: =SUMPRODUCT($AL15:$AP15,Weights!$R$28:$V$28) -> 1.3 | BA15: =IF($AR15<=1.6,"Low",IF($AR15<=2.2,"Medium","High")) -> Low | BB15: =IF(OR($AT15="Yes",$AP15=5),"High",$BA15) -> Low
A16: NAT-hi | B16: Nationwide / the personal account used for business, adverse reading | C16: Individual | D16: Natural person | E16: Employed or pension | F16: No match | G16: No match | H16: United Kingdom | I16: UK tax residence only | J16: UK only | K16: Current account with credit | L16: Under 2k a month | M16: Enabled, unused | N16: Sole party | O16: Digital, own app | P16: Electronic, one source | Q16: Direct | R16: Under 5k, consistent | S16: 10 to 30 percent | T16: None | U16: Named businesses | V16: Consistent | W16: =INDEX(Mapping!$C$2:$C$99,MATCH("C1|"&C16,Mapping!$D$2:$D$99,0)) -> 1 | X16: =INDEX(Mapping!$C$2:$C$99,MATCH("C2|"&D16,Mapping!$D$2:$D$99,0)) -> 1 | Y16: =INDEX(Mapping!$C$2:$C$99,MATCH("C3|"&E16,Mapping!$D$2:$D$99,0)) -> 1 | Z16: =INDEX(Mapping!$C$2:$C$99,MATCH("C4|"&F16,Mapping!$D$2:$D$99,0)) -> 1 | AA16: =INDEX(Mapping!$C$2:$C$99,MATCH("C5|"&G16,Mapping!$D$2:$D$99,0)) -> 1 | AB16: =INDEX(Mapping!$C$2:$C$99,MATCH("G1|"&H16,Mapping!$D$2:$D$99,0)) -> 1 | AC16: =INDEX(Mapping!$C$2:$C$99,MATCH("G2|"&I16,Mapping!$D$2:$D$99,0)) -> 1 | AD16: =INDEX(Mapping!$C$2:$C$99,MATCH("G3|"&J16,Mapping!$D$2:$D$99,0)) -> 1 | AE16: =INDEX(Mapping!$C$2:$C$99,MATCH("P1|"&K16,Mapping!$D$2:$D$99,0)) -> 3 | AF16: =INDEX(Mapping!$C$2:$C$99,MATCH("P2|"&L16,Mapping!$D$2:$D$99,0)) -> 3 | AG16: =INDEX(Mapping!$C$2:$C$99,MATCH("P3|"&M16,Mapping!$D$2:$D$99,0)) -> 2 | AH16: =INDEX(Mapping!$C$2:$C$99,MATCH("P4|"&N16,Mapping!$D$2:$D$99,0)) -> 1 | AI16: =INDEX(Mapping!$C$2:$C$99,MATCH("D1|"&O16,Mapping!$D$2:$D$99,0)) -> 3 | AJ16: =INDEX(Mapping!$C$2:$C$99,MATCH("D2|"&P16,Mapping!$D$2:$D$99,0)) -> 4 | AK16: =INDEX(Mapping!$C$2:$C$99,MATCH("D3|"&Q16,Mapping!$D$2:$D$99,0)) -> 1 | AL16: =INDEX(Mapping!$C$2:$C$99,MATCH("A1|"&R16,Mapping!$D$2:$D$99,0)) -> 1 | AM16: =INDEX(Mapping!$C$2:$C$99,MATCH("A2|"&S16,Mapping!$D$2:$D$99,0)) -> 3 | AN16: =INDEX(Mapping!$C$2:$C$99,MATCH("A3|"&T16,Mapping!$D$2:$D$99,0)) -> 1 | AO16: =INDEX(Mapping!$C$2:$C$99,MATCH("A4|"&U16,Mapping!$D$2:$D$99,0)) -> 2 | AP16: =INDEX(Mapping!$C$2:$C$99,MATCH("A5|"&V16,Mapping!$D$2:$D$99,0)) -> 1 | AQ16: =SUMPRODUCT($W16:$AP16,Weights!$C$27:$V$27) -> 1.5975 | AR16: =ROUND($AQ16,2) -> 1.6 | AS16: =IF($AR16<=2,"Low",IF($AR16<=3.49,"Medium","High")) -> Low | AT16: =IF(OR($Z16>=3,$Y16=5,$X16=5,$W16=5,$AA16=5,$AB16=5,$AC16=5,$AD16=5),"Yes","No") -> No | AU16: =IF($AT16="Yes","High",$AS16) -> Low | AV16: =SUMPRODUCT($W16:$AA16,Weights!$C$28:$G$28) -> 1 | AW16: =SUMPRODUCT($AB16:$AD16,Weights!$H$28:$J$28) -> 1 | AX16: =SUMPRODUCT($AE16:$AH16,Weights!$K$28:$N$28) -> 2.45 | AY16: =SUMPRODUCT($AI16:$AK16,Weights!$O$28:$Q$28) -> 2.95 | AZ16: =SUMPRODUCT($AL16:$AP16,Weights!$R$28:$V$28) -> 1.75 | BA16: =IF($AR16<=1.6,"Low",IF($AR16<=2.2,"Medium","High")) -> Low | BB16: =IF(OR($AT16="Yes",$AP16=5),"High",$BA16) -> Low
B18: Reconstructions rated High at onboarding | C18: =COUNTIF($AU$4:$AU$16,"High") -> 5
B19: Reconstructions rated High by the arithmetic alone | C19: =COUNTIF($AS$4:$AS$16,"High") -> 0
